{
  "auth.basic.failed": "認証に失敗しました",
  "auth.basic.generated_token1": "1. MyAppページを開きます (先にログインしておく必要があります):\n\nhttps:\/\/www.dropbox.com\/developers\/apps\n\n2. \"Create App\"をクリックして進みます\n3. \"{{.API}}\"を選択\n4. \"{{.TypeOfAccess}}\"を選択\n5. アプリケーション名をつけて入力してください\n6. \"Create App\"をクリックして進みます\n7. \"Generated access token\"欄の近くにある\"Generate\"ボタンを押します\n8. 生成されたトークン文字列をコピーします\n",
  "auth.basic.generated_token2": "生成されたトークンを入力してください:",
  "auth.basic.oauth_seq1": "1. 次のURLを開き認証ダイアログを開いてください:\n\n{{.Url}}\n\n2. 'Allow'をクリックします (先にログインしておく必要があります):\n3. 認証コードをコピーします:",
  "auth.basic.oauth_seq2": "認証コードを入力してください",
  "auth.basic.user_cancelled": "要求により処理は中断されました",
  "auth.basic.verify.failed": "トークンの検証に失敗したか、不正なトークンです再試行してください",
  "auth.failed_or_cancelled": "認証に失敗またはキャンセルされました: {{.Cause}}",
  "flow.error.file_not_found": "ファイルが見つかりませんでした: `{{.Path}}`",
  "flow.error.no_file_path": "ファイルが指定されていません",
  "flow.error.not_a_file": "ファイルではありません: `{{.Path}}`",
  "flow.error.unable_to_read": "指定されたパスのファイル `{{.Path}}` がエラー {{.Error}} のため読み取れません",
  "infra.control.app_opt.common_opts.flag.concurrency": "指定した並列度で並列処理を行います",
  "infra.control.app_opt.common_opts.flag.concurrency.default": "プロセッサー数",
  "infra.control.app_opt.common_opts.flag.debug": "デバッグモードを有効にする",
  "infra.control.app_opt.common_opts.flag.proxy": "HTTP\/HTTPS プロクシ (ホスト名:ポート番号)",
  "infra.control.app_opt.common_opts.flag.quiet": "エラー以外のメッセージを抑制し、出力をJSONLフォーマットに変更します",
  "infra.control.app_opt.common_opts.flag.secure": "トークンをファイルに保存しません",
  "infra.control.app_opt.common_opts.flag.bandwidth": "コンテンツをアップロードまたはダウンロードする際の帯域幅制限(Kバイト毎秒)0の場合、制限を行わない",
  "infra.control.app_opt.common_opts.flag.workspace": "ワークスペースへのパス",
  "raw": "{{.Raw}}",
  "recipe.dev.async_vo.flag.peer": "アカウントの別名",
  "recipe.dev.async_vo.flag.run_concurrently": "並列実行",
  "recipe.dev.async.title": "非同期処理フレームワークテスト",
  "recipe.dev.doc_vo.flag.badge": "ビルド状態のバッジを含める",
  "recipe.dev.doc_vo.flag.filename": "ファイル名",
  "recipe.dev.doc_vo.flag.test": "テストモード",
  "recipe.dev.doc_vo.flag.markdown_readme": "READMEをMarkdownフォーマットで生成",
  "recipe.dev.doc.title": "ドキュメントを生成",
  "recipe.dev.doc.commands.header.command": "コマンド",
  "recipe.dev.doc.commands.header.description": "説明",
  "recipe.dev.doc.options.header.option": "オプション",
  "recipe.dev.doc.options.header.description": "説明",
  "recipe.dev.doc.options.header.default": "デフォルト",
  "recipe.dev.doc.options.body.option": "`-{{.Option}}`",
  "recipe.dev.doc.report.header.name": "列",
  "recipe.dev.doc.report.header.description": "説明",
  "recipe.dev.dummy_vo.flag.dest": "ダミーファイルの位置",
  "recipe.dev.dummy_vo.flag.max_entry": "最大エントリ数",
  "recipe.dev.dummy_vo.flag.path": "ダミーファイルエントリへのパス",
  "recipe.dev.dummy.title": "ダミーファイルを作成します",
  "recipe.dev.preflight_vo.flag.test":"テストモード",
  "recipe.dev.preflight.title":"リリースに向けて必要な事前準備を実施",
  "recipe.dev.doc_vo.flag.lang":"言語",
  "recipe.dev.doc_vo.flag.command_path":"コマンドマニュアルを作成する相対パス",
  "recipe.dev.test.auth_vo.flag.audit": "Dropbox Business Audit スコープで認証",
  "recipe.dev.test.auth_vo.flag.file": "Dropbox Business member file access スコープで認証",
  "recipe.dev.test.auth_vo.flag.full": "Dropbox user full access スコープで認証",
  "recipe.dev.test.auth_vo.flag.info": "Dropbox Business info スコープで認証",
  "recipe.dev.test.auth_vo.flag.mgmt": "Dropbox Business management スコープで認証",
  "recipe.dev.test.auth.title": "エンドツーエンドテストのための認証",
  "recipe.dev.test.recipe_vo.flag.all": "全てのレシピをテストします",
  "recipe.dev.test.recipe_vo.flag.recipe": "テストするレシピ名",
  "recipe.dev.test.recipe_vo.flag.resource": "テスト用リソースへのパス",
  "recipe.dev.test.recipe.title": "レシピのテスト",
  "recipe.dev.test.resources.title": "バイナリの品質テスト",
  "recipe.dev.test.title": "バイナリテスト",
  "recipe.dev.title": "開発用レシピ",
  "recipe.file.compare.account_vo.flag.left_path": "アカウントのルートからのパス (左)",
  "recipe.file.compare.account_vo.flag.left": "アカウントの別名 (左)",
  "recipe.file.compare.account_vo.flag.right_path": "アカウントのルートからのパス (右)",
  "recipe.file.compare.account_vo.flag.right": "アカウントの別名 (右)",
  "recipe.file.compare.account.conn_left": "アカウントに認証します (左)",
  "recipe.file.compare.account.conn_right": "アカウントに認証します (右)",
  "recipe.file.compare.account.success": "{{.DiffCount}} 件の差分が見つかりました",
  "recipe.file.compare.account.title": "二つのアカウントのファイルを比較します",
  "recipe.file.compare.account.cli.args": "-left left -left-path \/path\/to\/compare -right right -right-path \/path\/to\/compare",
  "recipe.file.compare.account.cli.note": "同じアカウント内の別パス同士を比較したい場合には `-left` と `-right` に同じ別名を指定してください",
  "recipe.file.compare.local_vo.flag.peer": "アカウントの別名",
  "recipe.file.compare.local_vo.flag.local_path": "ローカルパス",
  "recipe.file.compare.local_vo.flag.dropbox_path": "Dropbox上のパス",
  "recipe.file.compare.local.title": "ローカルフォルダとDropboxフォルダの内容を比較します",
  "recipe.file.compare.local.cli.args": "-local-path \/path\/to\/local -dropbox-path \/path\/on\/dropbox",
  "recipe.file.compare.local.success": "{{.DiffCount}} 件の差分が見つかりました",
  "recipe.file.compare.title": "ファイルの比較",
  "recipe.file.copy_vo.flag.dst": "宛先のパス",
  "recipe.file.copy_vo.flag.peer": "アカウントの別名",
  "recipe.file.copy_vo.flag.src": "元のパス",
  "recipe.file.copy.title": "ファイルをコピーします",
  "recipe.file.copy.cli.args": "-src \/SRC\/PATH -dst \/DST\/PATH",
  "recipe.file.upload.title": "ファイルのアップロード",
  "recipe.file.upload_vo.flag.peer": "アカウントの別名",
  "recipe.file.upload_vo.flag.local_path": "ローカルファイルのパス",
  "recipe.file.upload_vo.flag.dropbox_path": "転送先のDropboxパス",
  "recipe.file.upload_vo.flag.overwrite": "既存のファイルを上書きします",
  "recipe.file.upload_vo.flag.chunk_size": "アップロードチャンク容量(Kバイト)",
  "recipe.file.upload.cli.args": "-local-path \/PATH\/TO\/UPLOAD -dropbox-path \/DROPBOX\/PATH",
  "recipe.file.import.batch.title": "ファイルを一括でインポートします",
  "recipe.file.import.batch.url_vo.flag.data": "データファイル",
  "recipe.file.import.batch.url_vo.flag.path": "インポート先のパス",
  "recipe.file.import.batch.url_vo.flag.peer": "アカウントの別名",
  "recipe.file.import.batch.url.err.path_missing": "インポート用のパスが指定されていません",
  "recipe.file.import.batch.url.progress": "ダウンロード中: `{{.Url}}` to `{{.Path}}`",
  "recipe.file.import.batch.url.title": "URLからファイルを一括インポートします",
  "recipe.file.import.batch.url.cli.args": "-data \/path\/to\/data\/file -path \/path\/to\/import",
  "recipe.file.import.title": "ファイルのインポート",
  "recipe.file.import.url_vo.flag.path": "インポート先のパス",
  "recipe.file.import.url_vo.flag.peer": "アカウントの別名",
  "recipe.file.import.url_vo.flag.url": "URL",
  "recipe.file.import.url.progress": "ファイルをインポートしています: `{{.Url}}` から `{{.Path}} へ`",
  "recipe.file.import.url.title": "URLからファイルをインポートします",
  "recipe.file.import.url.cli.args": "-url URL -path \/path\/to\/import",
  "recipe.file.sync.up_vo.flag.peer": "アカウントの別名",
  "recipe.file.sync.up_vo.flag.local_path": "ローカルファイルのパス",
  "recipe.file.sync.up_vo.flag.dropbox_path": "転送先のDropboxパス",
  "recipe.file.sync.title": "Dropboxとファイルを同期",
  "recipe.file.sync.up.title": "Dropboxと上り方向で同期します",
  "recipe.file.sync.preflight.up.title": "上り方向同期のための事前チェックを実施します",
  "recipe.file.sync.preflight.up_vo.flag.peer": "アカウントの別名",
  "recipe.file.sync.preflight.up_vo.flag.local_path": "ローカルファイルのパス",
  "recipe.file.sync.preflight.up_vo.flag.dropbox_path": "転送先のDropboxパス",
  "recipe.file.sync.preflight.title": "同期の事前チェック",
  "recipe.file.list_vo.flag.include_deleted": "削除済みファイルを含める",
  "recipe.file.list_vo.flag.include_media_info": "メディア情報を含める",
  "recipe.file.list_vo.flag.path": "パス",
  "recipe.file.list_vo.flag.peer": "アカウントの別名",
  "recipe.file.list_vo.flag.recursive": "再起的に一覧を実行",
  "recipe.file.list.title": "ファイルとフォルダを一覧します",
  "recipe.file.list.cli.args": "-path \/path",
  "recipe.file.merge_vo.flag.dry_run": "リハーサルを行います",
  "recipe.file.merge_vo.flag.from": "統合するパス",
  "recipe.file.merge_vo.flag.keep_empty_folder": "統合後に空となったフォルダを維持する",
  "recipe.file.merge_vo.flag.peer": "アカウントの別名",
  "recipe.file.merge_vo.flag.to": "統合するパス",
  "recipe.file.merge_vo.flag.within_same_namespace": "ネームスペースを超えないように制御します. これは共有リンクを含む共有権限設定を維持するためです.",
  "recipe.file.merge.title": "フォルダを統合します",
  "recipe.file.merge.cli.args": "-from \/from\/path -to \/path\/to",
  "recipe.file.merge.cli.note": "期待する結果と整合性があうことを確認できたら`-dry-run=false` オプションを追加して実行してください",
  "recipe.file.move_vo.flag.dst": "宛先のパス",
  "recipe.file.move_vo.flag.peer": "アカウントの別名",
  "recipe.file.move_vo.flag.src": "元のパス",
  "recipe.file.move.title": "ファイルを移動します",
  "recipe.file.move.cli.args": "-src \/SRC\/PATH -dst \/DST\/PATH",
  "recipe.file.replication_vo.flag.dst_path": "宛先のパス",
  "recipe.file.replication_vo.flag.dst": "アカウントの別名 (宛先)",
  "recipe.file.replication_vo.flag.src_path": "元のパス",
  "recipe.file.replication_vo.flag.src": "アカウントの別名 (元)",
  "recipe.file.replication.conn_dst": "アカウントの別名 (宛先)",
  "recipe.file.replication.conn_src": "アカウントの別名 (元)",
  "recipe.file.replication.done": "複製が完了しました: {{.DiffCount}} 件の差分が検出されました",
  "recipe.file.replication.title": "ファイルコンテンツを他のアカウントに複製します",
  "recipe.file.replication.cli.args": "-src source -src-path \/path\/src -dst dest -dst-path \/path\/dest",
  "recipe.file.replication.desc": "このコマンドはファイルとフォルダを複製します. しかし、ファイルの共有権限については複製しません. このコマンドは指定されたパスのフォルダコンテンツのみを複製します",
  "recipe.file.title": "ファイル操作",
  "recipe.group.delete_vo.flag.name": "グループ名",
  "recipe.group.delete_vo.flag.peer": "アカウントの別名",
  "recipe.group.delete.err.missing_option.name": "必須オプションの `name`が指定されていません",
  "recipe.group.delete.err.unable_to_remove_group": "グループを削除する際にエラーが発生しました: {{.Error}}",
  "recipe.group.delete.err.unable_to_resolve_group": "グループの情報を取得することができませんでした: {{.Error}}",
  "recipe.group.delete.success.removed": "グループが削除されました; グループ名: {{.GroupName}}, 管理タイプ: {{.ManagementType}}",
  "recipe.group.delete.title": "グループを削除します",
  "recipe.group.delete.cli.args": "-name グループ名",
  "recipe.group.delete.desc": "このコマンドはグループがフォルダなどで利用されているかどうかを確認しない点ご注意ください",
  "recipe.group.list_vo.flag.peer": "アカウントの別名",
  "recipe.group.list.title": "グループを一覧",
  "recipe.group.member.list_vo.flag.peer": "アカウントの別名",
  "recipe.group.member.list.progress.scan": "情報を取得中: {{.Group}}",
  "recipe.group.member.list.title": "グループに所属するメンバー一覧を取得します",
  "recipe.group.member.title": "グループメンバー",
  "recipe.group.title": "グループの管理 (Dropbox Business)",
  "recipe.license.third_party_notice.body": "このドキュメントはライセンス情報ならびに、本ソフトウエアが利用しているフリーソフトウエアまたはオープンソースソフトウエアのライセンス情報を含みます.\n`watermint toolbox`に含まれるサードパーティソフトウエア:",
  "recipe.license.third_party_notice.head": "watermint toolbox サードパーティ・ソフトウエアについて",
  "recipe.license.title": "ライセンス情報を表示します",
  "recipe.member.delete_vo.flag.file": "データファイル",
  "recipe.member.delete_vo.flag.peer": "アカウントの別名",
  "recipe.member.delete_vo.flag.wipe_data": "指定した場合にはユーザーのデータがリンクされたデバイスから削除されます",
  "recipe.member.delete.title": "メンバーを削除します",
  "recipe.member.delete.cli.args": "-file \/path\/to\/data\/file.csv",
  "recipe.member.detach_vo.flag.file": "データファイル",
  "recipe.member.detach_vo.flag.peer": "アカウントの別名",
  "recipe.member.detach_vo.flag.revoke_team_shares": "指定した場合にはユーザーからチームが保有する共有フォルダからのアクセス権を剥奪します",
  "recipe.member.detach.title": "Dropbox BusinessユーザーをBasicユーザーに変更します",
  "recipe.member.detach.cli.args": "-file \/path\/to\/data\/file.csv",
  "recipe.member.invite_vo.flag.file": "データファイル",
  "recipe.member.invite_vo.flag.peer": "アカウントの別名",
  "recipe.member.invite_vo.flag.silent_invite": "ウエルカムメールを送信しません (SSOとドメイン確認が必要です)",
  "recipe.member.invite.tag.user_already_on_team": "ユーザーはすでにチームに参加しています",
  "recipe.member.invite.tag.user_on_another_team": "ユーザーは他のチームに参加しています",
  "recipe.member.invite.title": "メンバーを招待します",
  "recipe.member.invite.cli.args": "-file \/path\/to\/data\/file.csv",
  "recipe.member.list_vo.flag.peer": "アカウントの別名",
  "recipe.member.list.title": "チームメンバーの一覧",
  "recipe.member.quota.list_vo.flag.peer": "アカウントの別名",
  "recipe.member.quota.list.scan": "メンバーの情報を取得中: {{.MemberEmail}}",
  "recipe.member.quota.list.title": "メンバーの容量制限情報を一覧します",
  "recipe.member.quota.title": "メンバーの容量制限管理",
  "recipe.member.quota.update_vo.flag.file": "データファイル",
  "recipe.member.quota.update_vo.flag.peer": "アカウントの別名",
  "recipe.member.quota.update.err.cannot_update": "メンバーの容量制限を変更できませんでした: {{.Error}}",
  "recipe.member.quota.update.err.member_not_found_for_email": "メンバーが指定されたメールアドレスでは見つかりませんでした: {{.Email}}",
  "recipe.member.quota.update.err.not_found": "メンバーが指定されたメールアドレスでは見つかりませんでした: {{.Email}}",
  "recipe.member.quota.update.progress": "メンバーの容量制限を変更しています; メンバー:{{.MemberEmail}}, 容量制限:{{.Quota}}",
  "recipe.member.quota.update.skip.same_from_to_email": "変更先と変更元が同じアドレスです",
  "recipe.member.quota.update.skip.unverified_email": "メールアドレスが確認されていないアカウントをスキップします",
  "recipe.member.quota.update.title": "チームメンバーの容量制限を変更",
  "recipe.member.quota.usage_vo.flag.peer": "アカウントの別名",
  "recipe.member.quota.usage.scan": "メンバーの情報を取得中: {{.MemberEmail}}",
  "recipe.member.quota.usage.title": "チームメンバーのストレージ利用状況を取得",
  "recipe.member.replication_vo.flag.dst": "宛先チーム; チームのファイルアクセス",
  "recipe.member.replication_vo.flag.file": "データファイル",
  "recipe.member.replication_vo.flag.src": "元チーム; チームのファイルアクセス",
  "recipe.member.replication.conn_dst_file": "認証: 宛先チームのファイルアクセス",
  "recipe.member.replication.conn_src_file": "認証: 元チームのファイルアクセス",
  "recipe.member.replication.progress": "メンバーデータを複製中: {{.SrcEmail}} -> {{.DstEmail}}",
  "recipe.member.replication.title": "チームメンバーのファイルを複製します",
  "recipe.member.title": "チームメンバーの管理 (Dropbox Business)",
  "recipe.member.update.email_vo.flag.update_unverified": "アカウントのメールアドレスが確認されていない場合でも変更する. アカウントのメールアドレスが確認されていない場合、フォルダへの招待を失う場合があります.",
  "recipe.member.update.email_vo.flag.file": "データファイル",
  "recipe.member.update.email_vo.flag.peer": "アカウントの別名",
  "recipe.member.update.email.err.api_error": "メールアドレスを変更できませんでした; 理由: {{.Error}}",
  "recipe.member.update.email.err.internal_error_clone": "処理できませんでした",
  "recipe.member.update.email.progress.updating": "変更中: {{.EmailFrom}} -> {{.EmailTo}}",
  "recipe.member.update.email.title": "メンバーのメールアドレス処理",
  "recipe.member.update.email.cli.args": "-file \/path\/to\/data\/file.csv",
  "recipe.member.update.profile_vo.flag.file": "データファイル",
  "recipe.member.update.profile_vo.flag.peer": "アカウントの別名",
  "recipe.member.update.profile.progress": "メンバーのプロフィール変更: {{.Email}}",
  "recipe.member.update.profile.title": "メンバーのプロフィール変更",
  "recipe.member.update.profile.cli.args": "-file \/path\/to\/data\/file.csv",
  "recipe.member.update.title": "Emailアドレスを一括変更",
  "recipe.sharedfolder.list_vo.flag.peer": "アカウントの別名",
  "recipe.sharedfolder.list.title": "共有フォルダの一覧",
  "recipe.sharedfolder.member.list_vo.flag.peer": "アカウントの別名",
  "recipe.sharedfolder.member.list.progress.scan": "フォルダをスキャンしています: {{.Folder}} (共有フォルダID: {{.FolderId}})",
  "recipe.sharedfolder.member.list.title": "共有フォルダのメンバーを一覧します",
  "recipe.sharedfolder.member.title": "共有フォルダのメンバー",
  "recipe.sharedfolder.title": "共有フォルダ",
  "recipe.sharedlink.create_vo.flag.expires": "共有リンクの有効期限日時",
  "recipe.sharedlink.create_vo.flag.password": "パスワード",
  "recipe.sharedlink.create_vo.flag.path": "パス",
  "recipe.sharedlink.create_vo.flag.peer": "アカウントの別名",
  "recipe.sharedlink.create_vo.flag.team_only": "リンクがチームメンバーのみアクセスできます",
  "recipe.sharedlink.create.err.unsupported_time_format": "未対応の日時フォーマットです: `{{.Input}}`",
  "recipe.sharedlink.create.success": "共有リンクが作成されました: {{.Url}}",
  "recipe.sharedlink.create.title": "共有リンクの作成",
  "recipe.sharedlink.create.cli.args": "-path \/path\/to\/share",
  "recipe.sharedlink.list_vo.flag.peer": "アカウントの別名",
  "recipe.sharedlink.list.title": "共有リンクの一覧",
  "recipe.sharedlink.delete_vo.flag.path": "共有リンクを削除するファイルまたはフォルダへのパス",
  "recipe.sharedlink.delete_vo.flag.peer": "アカウントの別名",
  "recipe.sharedlink.delete_vo.flag.recursive": "フォルダ階層をたどって削除します",
  "recipe.sharedlink.delete.err.unable_to_remove": "エラーが発生したためリンクを削除できませんでした `{{.Error}}`",
  "recipe.sharedlink.delete.info.no_links_at_the_path": "指定されたパスには共有リンクは見つかりませんでした: `{{.Path}}`",
  "recipe.sharedlink.delete.progress": "リンクを削除しています; URL:`{{.Url}}` パス:`{{.Path}}`",
  "recipe.sharedlink.delete.title": "共有リンクを削除します",
  "recipe.sharedlink.delete.cli.args": "-path \/path\/to\/delete",
  "recipe.sharedlink.delete.desc": "このコマンドはDropbox内のパスを指定して共有リンクを削除します",
  "recipe.sharedlink.title": "個人アカウントの共有リンク",
  "recipe.team.activity.daily.event_vo.flag.category": "イベントのカテゴリ",
  "recipe.team.activity.daily.event_vo.flag.end_date": "終了日",
  "recipe.team.activity.daily.event_vo.flag.peer": "アカウントの別名",
  "recipe.team.activity.daily.event_vo.flag.start_date": "開始日",
  "recipe.team.activity.daily.event.progress": "{{.Start}} から {{.End}} のアクティビティを取得しています",
  "recipe.team.activity.daily.event.title": "アクティビティーを1日ごとに取得します",
  "recipe.team.activity.daily.title": "チームの1日ごとのアクティビティ",
  "recipe.team.activity.daily.cli.args": "-start-date 2019-11-05",
  "recipe.team.activity.event_vo.flag.category": "一つのイベントカテゴリのみを返すようなフィルター条件. このフィールドはオプションです.",
  "recipe.team.activity.event_vo.flag.end_time": "終了日時 (該当同時刻を含まない).",
  "recipe.team.activity.event_vo.flag.peer": "アカウントの別名",
  "recipe.team.activity.event_vo.flag.start_time": "開始日時 (該当時刻を含む)",
  "recipe.team.activity.event.title": "イベントログ",
  "recipe.team.activity.title": "チームのアクティビティチーム情報",
  "recipe.team.device.list_vo.flag.peer": "アカウントの別名",
  "recipe.team.device.list.title": "チーム内全てのデバイス\/セッションを一覧します",
  "recipe.team.device.title": "メンバーのデバイス",
  "recipe.team.device.unlink_vo.flag.delete_on_unlink": "デバイスリンク解除時にファイルを削除します",
  "recipe.team.device.unlink_vo.flag.file": "データファイル",
  "recipe.team.device.unlink_vo.flag.peer": "アカウントの別名",
  "recipe.team.device.unlink.err.unable_to_unlink": "セッションがリンク解除できませんでした: {{.Error}}",
  "recipe.team.device.unlink.progress": "セッションを解除; メンバー: {{.Member}}, タイプ: {{.SessionType}}, セッションID: {{.SessionId}}",
  "recipe.team.device.unlink.title": "デバイスのセッションを解除します",
  "recipe.team.device.unlink.cli.args": "-file \/path\/to\/data\/file.csv",
  "recipe.team.diagnosis_vo.flag.include_file_list": "ネームスペースのファイルを含める",
  "recipe.team.diagnosis_vo.flag.peer": "アカウントの別名",
  "recipe.team.diagnosis.title": "チームの情報を出力します",
  "recipe.team.feature_vo.flag.peer": "アカウントの別名",
  "recipe.team.feature.title": "チームの機能を出力します",
  "recipe.team.filerequest.clone.err.cannot_create": ":ファイルリクエスト作成中にエラーが発生しました {{.Error}}",
  "recipe.team.filerequest.clone.err.no_member_found_for_email": "メールアドレスに該当するメンバーが見つかりませんでした",
  "recipe.team.filerequest.clone.title": "ファイルリクエストを入力データに従い複製します",
  "recipe.team.filerequest.list_vo.flag.peer": "アカウントの別名",
  "recipe.team.filerequest.list.scan": "メンバーの情報を取得中: {{.MemberEmail}}",
  "recipe.team.filerequest.list.title": "チームないのファイルリクエストを一覧します",
  "recipe.team.filerequest.title": "チーム内のファイルリクエスト",
  "recipe.team.info_vo.flag.peer": "アカウントの別名",
  "recipe.team.info.title": "チームの情報",
  "recipe.team.linkedapp.list_vo.flag.peer": "アカウントの別名",
  "recipe.team.linkedapp.list.title": "リンク済みアプリを一覧",
  "recipe.team.linkedapp.title": "リンク済みアプリ",
  "recipe.team.namespace.file.list_vo.flag.include_deleted": "指定された場合、削除済みのファイルやフォルダが含めます",
  "recipe.team.namespace.file.list_vo.flag.include_media_info": "指定された場合、JSONレポートに写真や動画ファイルへのメデイア情報を含めます",
  "recipe.team.namespace.file.list_vo.flag.include_member_folder": "指定された場合、チームメンバーのフォルダを含めます",
  "recipe.team.namespace.file.list_vo.flag.include_shared_folder": "指定された場合、共有フォルダを含めます",
  "recipe.team.namespace.file.list_vo.flag.include_team_folder": "指定された場合、チームフォルダを含めます",
  "recipe.team.namespace.file.list_vo.flag.name": "指定された名前に一致するフォルダのみを一覧します",
  "recipe.team.namespace.file.list_vo.flag.peer": "アカウントの別名",
  "recipe.team.namespace.file.list.err.scan_failed": "ネームスペースのスキャンに失敗しました: {{.NamespaceName}} ({{.NamespaceId}}), caused by an error: {{.Error}}",
  "recipe.team.namespace.file.list.scan": "ファイルをスキャンしています: {{.NamespaceName}} ({{.NamespaceId}})",
  "recipe.team.namespace.file.list.title": "チーム内全ての名前空間でのファイル・フォルダを一覧",
  "recipe.team.namespace.file.size_vo.flag.depth": "フォルダ階層数の指定",
  "recipe.team.namespace.file.size_vo.flag.include_shared_folder": "指定された場合、共有フォルダを含めます",
  "recipe.team.namespace.file.size_vo.flag.include_team_folder": "指定された場合、チームフォルダを含めます",
  "recipe.team.namespace.file.size_vo.flag.name": "指定された名前に一致するフォルダのみを一覧します",
  "recipe.team.namespace.file.size_vo.flag.peer": "アカウントの別名",
  "recipe.team.namespace.file.size.err.scan_failed": "ネームスペースのスキャンに失敗しました: {{.NamespaceName}} ({{.NamespaceId}}), caused by an error: {{.Error}}",
  "recipe.team.namespace.file.size.scan": "ファイルをスキャンしています: {{.NamespaceName}} ({{.NamespaceId}})",
  "recipe.team.namespace.file.size.title": "チーム内全ての名前空間でのファイル・フォルダを一覧",
  "recipe.team.namespace.file.title": "チームの名前空間ファイル管理",
  "recipe.team.namespace.list_vo.flag.peer": "アカウントの別名",
  "recipe.team.namespace.list.title": "チーム内すべての名前空間を一覧",
  "recipe.team.namespace.member.list_vo.flag.all_columns": "全てのカラムを表示します",
  "recipe.team.namespace.member.list_vo.flag.peer": "アカウントの別名",
  "recipe.team.namespace.member.list.scan": "メンバーの情報を取得しています: {{.NamespaceName}} ({{.NamespaceId}})",
  "recipe.team.namespace.member.list.title": "チームフォルダ以下のファイル・フォルダを一覧",
  "recipe.team.namespace.member.title": "チーム所有の名前空間からメンバーを一覧",
  "recipe.team.namespace.title": "チーム内の名前空間",
  "recipe.team.sharedlink.list_vo.flag.peer": "アカウントの別名",
  "recipe.team.sharedlink.list.scan": "メンバーの情報を取得中: {{.MemberEmail}}",
  "recipe.team.sharedlink.list.title": "共有リンクの一覧",
  "recipe.team.sharedlink.title": "チーム全体の共有リンク",
  "recipe.team.sharedlink.update.expiry_vo.flag.at": "新しい有効期限の日時",
  "recipe.team.sharedlink.update.expiry_vo.flag.days": "新しい有効期限までの日時",
  "recipe.team.sharedlink.update.expiry_vo.flag.peer": "アカウントの別名",
  "recipe.team.sharedlink.update.expiry_vo.flag.visibility": "Target link visibility",
  "recipe.team.sharedlink.update.expiry.scan": "メンバーの情報を取得中: {{.MemberEmail}}",
  "recipe.team.sharedlink.update.expiry.updating":"リンクの有効期限を更新しています; メンバー:{{.MemberEmail}}, Url:{{.Url}}, 有効期限:`{{.CurrentExpiry}}` -> `{{.NewExpiry}}`",
  "recipe.team.sharedlink.update.expiry.err.days_should_not_negative": "`days` オプションは1日以上を指定してください",
  "recipe.team.sharedlink.update.expiry.err.invalid_date_time_format_for_at_option": "`at` オプションの日時フォーマットが非対応の書式です",
  "recipe.team.sharedlink.update.expiry.err.please_specify_days_or_at": "`days`または`at`オプションを指定してください",
  "recipe.team.sharedlink.update.expiry.title": "チーム内の公開されている共有リンクについて有効期限を更新します",
  "recipe.team.sharedlink.update.expiry.cli.args": "-days 28",
  "recipe.team.sharedlink.update.title": "共有リンクの更新",
  "recipe.team.title": "Dropbox Business チーム",
  "recipe.teamfolder.archive_vo.flag.name": "チームフォルダ名",
  "recipe.teamfolder.archive_vo.flag.peer": "アカウントの別名",
  "recipe.teamfolder.archive.err.missing_option.name": "必須オプションの `name`が指定されていません",
  "recipe.teamfolder.archive.err.unable_to_remove_teamfolder": "チームフォルダのアーカイブに失敗しました: {{.Error}}",
  "recipe.teamfolder.archive.err.unable_to_resolve_teamfolder": "チームフォルダの情報取得に失敗しました: {{.Error}}",
  "recipe.teamfolder.archive.success.archived": "チームフォルダがアーカイブされました; チームフォルダ名:{{.TeamFolderName}}",
  "recipe.teamfolder.archive.title": "チームフォルダのアーカイブ",
  "recipe.teamfolder.archive.cli.args": "-name チームフォルダ名",
  "recipe.teamfolder.list_vo.flag.peer": "アカウントの別名",
  "recipe.teamfolder.list.title": "チームフォルダの一覧",
  "recipe.teamfolder.perm_delete_vo.flag.name": "チームフォルダ名",
  "recipe.teamfolder.perm_delete_vo.flag.peer": "アカウントの別名",
  "recipe.teamfolder.permdelete.err.missing_option.name": "必須オプションの `name`が指定されていません",
  "recipe.teamfolder.permdelete.err.unable_to_remove_teamfolder": "チームフォルダを完全に削除できませんでした: {{.Error}}",
  "recipe.teamfolder.permdelete.err.unable_to_resolve_teamfolder": "チームフォルダの情報取得に失敗しました: {{.Error}}",
  "recipe.teamfolder.permdelete.success.permdeleted": "チームフォルダが完全に削除されました; チームフォルダ名:{{.TeamFolderName}}",
  "recipe.teamfolder.permdelete.title": "チームフォルダを完全に削除します",
  "recipe.teamfolder.permdelete.cli.args": "-name チームフォルダ名",
  "recipe.teamfolder.replication_vo.flag.dst_file": "宛先チーム; チームのファイルアクセス",
  "recipe.teamfolder.replication_vo.flag.dst_mgmt": "宛先チーム: チーム管理権限",
  "recipe.teamfolder.replication_vo.flag.name": "チームフォルダ名",
  "recipe.teamfolder.replication_vo.flag.src_file": "元チーム; チームのファイルアクセス",
  "recipe.teamfolder.replication_vo.flag.src_mgmt": "元チーム: チーム管理権限",
  "recipe.teamfolder.replication.conn_src_file": "元チームに接続します: ファイルアクセス権限",
  "recipe.teamfolder.replication.conn_src_mgmt": "元チームに接続します: 管理権限",
  "recipe.teamfolder.replication.conn_dst_file": "宛先チームに接続します: ファイルアクセス権限",
  "recipe.teamfolder.replication.conn_dst_mgmt": "宛先チームに接続します: 管理権限",
  "recipe.teamfolder.replication.failure": "複製に失敗しました",
  "recipe.teamfolder.replication.success": "複製が完了しました",
  "recipe.teamfolder.replication.title": "チームフォルダを他のチームに複製します",
  "recipe.teamfolder.replication.cli.arsg": "-src-file source -src-mgmt source -dst-file dest -dst-mgmt dest -pname チームフォルダ名",
  "recipe.teamfolder.title": "チームフォルダの管理 (Dropbox Business)",
  "recipe.title": "DropboxおよびDropbox Business向けのツールセット",
  "recipe.web_vo.flag.port": "ポート番号",
  "recipe.web.title": "Webコンソールを起動 (実験的)",
  "report.empty_spec.desc_column": "カラムの仕様が定義されていません `{{.Column}}`",
  "report.empty_spec.desc": "空のレポート",
  "report.transaction.failure.invalid_data": "不正なデータ",
  "report.transaction.failure": "失敗",
  "report.transaction.skip": "スキップ",
  "report.transaction.success": "成功",
  "report.xlsx.unable_to_open": "xlsx レポート: レポート `{{.Path}}` の作成に失敗しました (エラー: {{.Error}})",
  "report.recipe.head": "このコマンドの出力レポート",
  "report.recipe.head_report": "レポート: {{.Name}}",
  "report.recipe.col_head.name": "列",
  "report.recipe.col_head.desc": "説明",
  "run.app.copyright": "© 2016-2019 Takayuki Okazaki",
  "run.app.header": "watermint toolbox {{.AppVersion}}",
  "run.app.license": "オープンソースライセンスのもと配布されています. 詳細は`license`コマンドでご覧ください.",
  "run.console.large_report": "{{.Num}} 件. レポートファイルを参照してください.",
  "run.console.open_artifact.error": "フォルダを開くことができませんでした: {{.Error}}",
  "run.console.open_artifact": "成果物フォルダを開きます: {{.Path}}",
  "run.console.point_artifact": "レポートが作成されました: {{.Path}}",
  "run.console.progress": "{{.Label}}: {{.Progress}} 件を処理中...",
  "run.error.interrupted.instruction": "ログとレポートは次のパスに格納されました: {{.JobPath}}",
  "run.error.interrupted": "処理が中断されました",
  "run.error.panic.instruction": "詳細はログとレポートファイルを参照してください",
  "run.error.panic": "プログラムが致命的エラーにより終了しました",
  "run.error.recipe.failed": "処理がエラーにより終了しました: {{.Error}}",
  "run.group.header.available_commands": "利用可能なコマンド:",
  "run.group.header.usage": "使い方:",
  "run.group.usage": "{{.Exec}} {{.Group}} コマンド",
  "run.network.error.unreachable": "`{{.Url}}`へのネットワーク接続に失敗しました.\nネットワークが利用可能であるかどうか、またプロクシサーバの設定が正しいか確認してください.\nプロクシサーバやファイアウォール下で利用される場合には`-proxy`オプションにてプロクシサーバを指定してください.\n詳細は下記記事をご参照ください.\nhttps:\/\/github.com\/watermint\/toolbox\/wiki\/app.common.diag.network.err.unreachable.ja\n\nエラー:\n{{.Error}}",
  "run.network.progress.testing.done": "完了",
  "run.network.progress.testing": "ネットワーク接続をテストしています...",
  "run.recipe.header.available_flags": "利用可能なオプション:",
  "run.recipe.header.usage": "使い方:",
  "run.recipe.usage": "{{.Exec}} {{.Recipe}} [option...] {{.Args}}",
  "usecase.uc_compare_local.scan_folder": "フォルダをスキャンしています: {{.Path}}",
  "usecase.uc_compare_paths.scan_folder": "フォルダをスキャンしています: {{.Path}}",
  "usecase.uc_file_merge.move_file": "{{.DryRun}}ファイルを移動: `{{.FromPath}}` から `{{.ToPath}}` へ",
  "usecase.uc_file_merge.move_folder": "{{.DryRun}}フォルダを移動: `{{.FromPath}}` から `{{.ToPath}}` へ",
  "usecase.uc_file_merge.remove_duplicated_file": "{{.DryRun}}重複ファイルを削除: {{.FromPath}}",
  "usecase.uc_file_merge.remove_empty_folder": "{{.DryRun}}空フォルダを削除: {{.FromPath}}",
  "usecase.uc_file_merge.remove_old_content": "{{.DryRun}}古いファイルを削除: {{.FromPath}}",
  "usecase.uc_file_upload.progress.upload": "アップロード中: {{.File}}",
  "usecase.uc_file_upload.progress.skip":"スキップされました: {{.File}}",
  "usecase.uc_file_upload.skip.dont_sync": "システムファイルのため無視されました",
  "usecase.uc_file_upload.skip.file_exists": "Dropboxに同一ファイルが見つかりました",
  "usecase.uc_teamfolder_mirror.err.unable_to_create_diff_report": "差分レポートの作成に失敗しました: {{.Error}}",
  "web.conn.business_audit.detail": "チームの情報ならびに、チームの詳細なアクティビティログ取得の権限",
  "web.conn.business_audit.header": "Dropbox Business (監査)",
  "web.conn.business_file.detail": "チームの情報ならびに、チームメンバーに対するアクション実行の権限",
  "web.conn.business_file.header": "Dropbox Business (ファイルアクセス)",
  "web.conn.business_info.detail": "チームの情報ならびに、利用統計などの情報アクセス権限",
  "web.conn.business_info.header": "Dropbox Business (情報アクセス)",
  "web.conn.business_management.detail": "チームの情報ならびに、ファイルやフォルダの参照・追加・編集・削除、共有情報の取得権限",
  "web.conn.business_management.header": "Dropbox Business (管理)",
  "web.conn.user_full.detail": "個人用Dropboxの全てのファイル・フォルダへのアクセス",
  "web.conn.user_full.header": "Dropboxへのフルアクセス",
  "web.error.command_not_found.detail": "カタログから再試行してください",
  "web.error.command_not_found.header": "コマンドが見つかりませんでした",
  "web.error.forbidden.detail": "認証情報が確認できませんでした与えられたURLからログインしてください",
  "web.error.forbidden.header": "許可されていません",
  "web.error.notfound.detail": "ページが見つかりませんでした",
  "web.error.notfound.header": "見つかりませんでした",
  "web.error.server.detail": "詳細はログを確認してください.",
  "web.error.server.header": "サーバーエラー",
  "web.home.message": "ようこそ {{.User}}",
  "web.job.result.failure": "失敗 (エラー: {{.Error}})",
  "web.job.result.success": "成功",
  "doc.readme.title": "DropboxおよびDropbox Business向けのツールセット",
  "doc.readme.head.license": "ライセンスと免責条項",
  "doc.readme.body.license": "watermint toolboxはMITライセンスのもと配布されています.\n詳細はファイル LICENSE.mdまたは LICENSE.txt ご参照ください.",
  "doc.readme.body.license_note": "以下にご留意ください:",
  "doc.readme.head.usage": "利用方法",
  "doc.readme.body.usage": "`tbx` にはたくさんの機能があります. オプションなしで実行をするとサポートされているコマンドやオプションの一覧が表示されます.\nつぎのように引数なしで実行すると利用可能なコマンド・オプションがご確認いただけます.",
  "doc.readme.head.commands": "コマンド",
  "domain.model.mo_activity.event.event_category.desc": "ひとつのイベントカテゴリでフィルターします",
  "domain.model.mo_activity.event.event_type_desc.desc": "特定タイプのアクション",
  "domain.model.mo_activity.event.event_type.desc": "イベントのタイプ",
  "domain.model.mo_activity.event.timestamp.desc": "イベントのタイムスタンプ",
  "domain.model.mo_device.membersession.abbreviated_name.desc": "ユーザーの省略名称",
  "domain.model.mo_device.membersession.account_id.desc": "ユーザーのアカウントID",
  "domain.model.mo_device.membersession.browser.desc": "Webセッションのブラウザ情報",
  "domain.model.mo_device.membersession.client_type.desc": "Dropboxデスクトップクライアントタイプ (Windows, macまたはlinux)",
  "domain.model.mo_device.membersession.client_version.desc": "Dropboxクライアントバージョン",
  "domain.model.mo_device.membersession.country.desc": "このセッションの最終アクティビティの国",
  "domain.model.mo_device.membersession.created.desc": "セッションが作成された日時",
  "domain.model.mo_device.membersession.device_name.desc": "デバイス名",
  "domain.model.mo_device.membersession.device_tag.desc": "セッションのタイプ (web_session, desktop_client, または mobile_client)",
  "domain.model.mo_device.membersession.display_name.desc": "ユーザーのDropboxアカウントの表示名称",
  "domain.model.mo_device.membersession.email.desc": "ユーザーのメールアドレス",
  "domain.model.mo_device.membersession.expires.desc": "このセッションが失効する日時",
  "domain.model.mo_device.membersession.external_id.desc": "このユーザーに関連づけられた外部ID",
  "domain.model.mo_device.membersession.familiar_name.desc": "ロケール依存の名前",
  "domain.model.mo_device.membersession.given_name.desc": "名",
  "domain.model.mo_device.membersession.host_name.desc": "デスクトップホストの名称",
  "domain.model.mo_device.membersession.id.desc": "セッションID",
  "domain.model.mo_device.membersession.ip_address.desc": "このセッションの昨秋アクティビティのIPアドレス",
  "domain.model.mo_device.membersession.is_delete_on_unlink_supported.desc": "アカウントのファイルをリンク解除時に削除を試みます",
  "domain.model.mo_device.membersession.last_carrier.desc": "このデバイスで利用された最後のキャリア",
  "domain.model.mo_device.membersession.os_version.desc": "ホストOSのバージョン",
  "domain.model.mo_device.membersession.os.desc": "ホストOSの情報",
  "domain.model.mo_device.membersession.platform.desc": "ホストプラットホームの情報",
  "domain.model.mo_device.membersession.status.desc": "チームにおけるメンバーのステータス(active\/invited\/suspended\/removed)",
  "domain.model.mo_device.membersession.surname.desc": "名字",
  "domain.model.mo_device.membersession.team_member_id.desc": "チームにおけるメンバーのID",
  "domain.model.mo_device.membersession.updated.desc": "このセッションの最終アクティビティの日時",
  "domain.model.mo_device.membersession.user_agent.desc": "ホストデバイスの情報",
  "domain.model.mo_file_diff.diff.diff_type.desc": "差分のタイプ`file_content_diff`: コンテンツハッシュの差分, `{left|right}_file_missing`: 左または右のファイルが見つからない, `{left|right}_folder_missing`: 左または右のフォルダが見つからない.",
  "domain.model.mo_file_diff.diff.left_hash.desc": "左ファイルのコンテンツハッシュ",
  "domain.model.mo_file_diff.diff.left_kind.desc": "フォルダまたはファイル",
  "domain.model.mo_file_diff.diff.left_path.desc": "左のパス",
  "domain.model.mo_file_diff.diff.left_size.desc": "左ファイルのサイズ",
  "domain.model.mo_file_diff.diff.right_hash.desc": "右ファイルのコンテンツハッシュ",
  "domain.model.mo_file_diff.diff.right_kind.desc": "フォルダまたはファイル",
  "domain.model.mo_file_diff.diff.right_path.desc": "右のパス",
  "domain.model.mo_file_diff.diff.right_size.desc": "右ファイルのサイズ",
  "domain.model.mo_file_size.namespacesize.count_descendant.desc": "このフォルダに含まれるファイル・フォルダ数",
  "domain.model.mo_file_size.namespacesize.count_file.desc": "このフォルダに含まれるファイル数",
  "domain.model.mo_file_size.namespacesize.count_folder.desc": "このフォルダに含まれるフォルダ数",
  "domain.model.mo_file_size.namespacesize.namespace_id.desc": "名前空間ID",
  "domain.model.mo_file_size.namespacesize.namespace_name.desc": "名前空間の名称",
  "domain.model.mo_file_size.namespacesize.namespace_type.desc": "名前異空間のタイプ (app_folder, shared_folder, team_folder, または team_member_folder)",
  "domain.model.mo_file_size.namespacesize.owner_team_member_id.desc": "メンバーフォルダまたはアプリフォルダである場合、その所有者チームメンバーのID",
  "domain.model.mo_file_size.namespacesize.path.desc": "フォルダへのパス",
  "domain.model.mo_file_size.namespacesize.size.desc": "フォルダのサイズ",
  "domain.model.mo_file.concreteentry.client_modified.desc": "ファイルの場合、更新日時はクライアントPC上でのタイムスタンプ",
  "domain.model.mo_file.concreteentry.content_hash.desc": "ファイルコンテンツのハッシュ",
  "domain.model.mo_file.concreteentry.id.desc": "ファイルへの一意なID",
  "domain.model.mo_file.concreteentry.name.desc": "名称",
  "domain.model.mo_file.concreteentry.parent_shared_folder_id.desc": "",
  "domain.model.mo_file.concreteentry.path_display.desc": "パス (表示目的で大文字小文字を区別する).",
  "domain.model.mo_file.concreteentry.path_lower.desc": "パス (すべて小文字に変換). これは常にスラッシュで始まります.",
  "domain.model.mo_file.concreteentry.revision.desc": "ファイルの現在バージョンの一意な識別子",
  "domain.model.mo_file.concreteentry.server_modified.desc": "Dropbox上で最後に更新された日時",
  "domain.model.mo_file.concreteentry.shared_folder_id.desc": "これが共有フォルダのマウントポイントである場合、ここにマウントされている共有フォルダのID。",
  "domain.model.mo_file.concreteentry.size.desc": "ファイルサイズ(バイト単位)",
  "domain.model.mo_file.concreteentry.tag.desc": "エントリーの種別`file`, `folder`, または `deleted`",
  "domain.model.mo_filerequest.memberfilerequest.account_id.desc": "ファイルリクエスト所有者のアカウントID",
  "domain.model.mo_filerequest.memberfilerequest.created.desc": "このファイルリクエストが作成された日時",
  "domain.model.mo_filerequest.memberfilerequest.deadline_allow_late_uploads.desc": "設定されている場合、締め切りを超えてもアップロードが許可されている",
  "domain.model.mo_filerequest.memberfilerequest.deadline.desc": "ファイルリクエストの締め切り.",
  "domain.model.mo_filerequest.memberfilerequest.destination.desc": "アップロードされたファイルが置かれるDropboxフォルダのパス",
  "domain.model.mo_filerequest.memberfilerequest.email.desc": "ファイルリクエスト所有者のメールアドレス",
  "domain.model.mo_filerequest.memberfilerequest.file_count.desc": "このファイルリクエストが受け取ったファイル数",
  "domain.model.mo_filerequest.memberfilerequest.file_request_id.desc": "ファイルリクエストID",
  "domain.model.mo_filerequest.memberfilerequest.given_name.desc": "ファイルリクエスト所有者の名",
  "domain.model.mo_filerequest.memberfilerequest.is_open.desc": "このファイルリクエストがオープンしているかどうか",
  "domain.model.mo_filerequest.memberfilerequest.status.desc": "ファイルリクエスト所有者ユーザーの状態 (active\/invited\/suspended\/removed)",
  "domain.model.mo_filerequest.memberfilerequest.surname.desc": "ファイルリクエスト所有者の名字",
  "domain.model.mo_filerequest.memberfilerequest.team_member_id.desc": "ファイルリクエスト所有者のチームメンバーとしてのID",
  "domain.model.mo_filerequest.memberfilerequest.title.desc": "ファイルリクエストのタイトル",
  "domain.model.mo_filerequest.memberfilerequest.url.desc": "ファイルリクエストのURL",
  "domain.model.mo_group_member.groupmember.access_type.desc": "グループにおけるユーザーの役割 (member\/owner)",
  "domain.model.mo_group_member.groupmember.account_id.desc": "ユーザーアカウントのID",
  "domain.model.mo_group_member.groupmember.email.desc": "ユーザーのメールアドレス",
  "domain.model.mo_group_member.groupmember.given_name.desc": "名",
  "domain.model.mo_group_member.groupmember.group_id.desc": "グループID",
  "domain.model.mo_group_member.groupmember.group_management_type.desc": "だれがこのグループを管理できるか (user_managed, company_managed, または system_managed)",
  "domain.model.mo_group_member.groupmember.group_name.desc": "グループ名称",
  "domain.model.mo_group_member.groupmember.status.desc": "チームにおけるメンバーのステータス(active\/invited\/suspended\/removed)",
  "domain.model.mo_group_member.groupmember.surname.desc": "名字",
  "domain.model.mo_group_member.groupmember.team_member_id.desc": "チームにおけるメンバーのID",
  "domain.model.mo_group.group.group_external_id.desc": " グループの外部IDこの任意のIDは管理者がグループに付加できます",
  "domain.model.mo_group.group.group_id.desc": "グループID",
  "domain.model.mo_group.group.group_management_type.desc": "だれがこのグループを管理できるか (user_managed, company_managed, または system_managed)",
  "domain.model.mo_group.group.group_name.desc": "グループ名称",
  "domain.model.mo_group.group.member_count.desc": "グループ内のメンバー数",
  "domain.model.mo_linkedapp.memberlinkedapp.abbreviated_name.desc": "ユーザーの省略名称",
  "domain.model.mo_linkedapp.memberlinkedapp.account_id.desc": "ユーザーのアカウントID",
  "domain.model.mo_linkedapp.memberlinkedapp.app_id.desc": "アプリケーションの固有ID",
  "domain.model.mo_linkedapp.memberlinkedapp.app_name.desc": "アプリケーション名称",
  "domain.model.mo_linkedapp.memberlinkedapp.display_name.desc": "ユーザーのDropboxアカウントの表示名称",
  "domain.model.mo_linkedapp.memberlinkedapp.email.desc": "ユーザーのメールアドレス",
  "domain.model.mo_linkedapp.memberlinkedapp.external_id.desc": "このユーザーに関連づけられた外部ID",
  "domain.model.mo_linkedapp.memberlinkedapp.familiar_name.desc": "ロケール依存の名前",
  "domain.model.mo_linkedapp.memberlinkedapp.given_name.desc": "名",
  "domain.model.mo_linkedapp.memberlinkedapp.is_app_folder.desc": "アプリケーションが専用フォルダにリンクするかどうか",
  "domain.model.mo_linkedapp.memberlinkedapp.linked.desc": "アプリケーションがリンクされた日時",
  "domain.model.mo_linkedapp.memberlinkedapp.publisher_url.desc": "アプリケーションパブリッシャーの名前",
  "domain.model.mo_linkedapp.memberlinkedapp.publisher.desc": "パブリッシャーのURL",
  "domain.model.mo_linkedapp.memberlinkedapp.status.desc": "チームにおけるメンバーのステータス(active\/invited\/suspended\/removed)",
  "domain.model.mo_linkedapp.memberlinkedapp.surname.desc": "名字",
  "domain.model.mo_linkedapp.memberlinkedapp.team_member_id.desc": "チームにおけるメンバーのID",
  "domain.model.mo_member_quota.memberquota.email.desc": "ユーザーのメールアドレス",
  "domain.model.mo_member_quota.memberquota.quota.desc": "カスタムの容量制限GB (1 TB = 1024 GB). 0の場合、容量制限をしません.",
  "domain.model.mo_member.member.abbreviated_name.desc": "ユーザーの省略名称",
  "domain.model.mo_member.member.account_id.desc": "ユーザーのアカウントID",
  "domain.model.mo_member.member.display_name.desc": "ユーザーのDropboxアカウントの表示名称",
  "domain.model.mo_member.member.email_verified.desc": "trueの場合、ユーザーのメールアドレスはユーザーによって所有されていることが確認されています.",
  "domain.model.mo_member.member.email.desc": "ユーザーのメールアドレス",
  "domain.model.mo_member.member.external_id.desc": "このユーザーに関連づけられた外部ID",
  "domain.model.mo_member.member.familiar_name.desc": "ロケール依存の名前",
  "domain.model.mo_member.member.given_name.desc": "名",
  "domain.model.mo_member.member.joined_on.desc": "メンバーがチームに参加した日時.",
  "domain.model.mo_member.member.member_folder_id.desc": "ユーザールートフォルダの名前空間ID.",
  "domain.model.mo_member.member.persistent_id.desc": "ユーザーに付加できる永続ID. 永続IDはSAML認証で利用する一意なIDです.",
  "domain.model.mo_member.member.role.desc": "ユーザーのチームでの役割 (team_admin, user_management_admin, support_admin, または member_only)",
  "domain.model.mo_member.member.status.desc": "チームにおけるメンバーのステータス(active\/invited\/suspended\/removed)",
  "domain.model.mo_member.member.surname.desc": "名字",
  "domain.model.mo_member.member.team_member_id.desc": "チームにおけるメンバーのID",
  "domain.model.mo_member.member.tag.desc": "処理のタグ",
  "domain.model.mo_namespace.namespace.name.desc": "名前空間の名称",
  "domain.model.mo_namespace.namespace.namespace_id.desc": "名前空間ID",
  "domain.model.mo_namespace.namespace.namespace_type.desc": "名前異空間のタイプ (app_folder, shared_folder, team_folder, または team_member_folder)",
  "domain.model.mo_namespace.namespace.team_member_id.desc": "メンバーフォルダまたはアプリフォルダである場合、その所有者チームメンバーのID",
  "domain.model.mo_namespace.namespaceentry.client_modified.desc": "ファイルの場合、更新日時はクライアントPC上でのタイムスタンプ",
  "domain.model.mo_namespace.namespaceentry.content_hash.desc": "ファイルコンテンツのハッシュ",
  "domain.model.mo_namespace.namespaceentry.file_id.desc": "ファイルへの一意なID",
  "domain.model.mo_namespace.namespaceentry.name.desc": "名称",
  "domain.model.mo_namespace.namespaceentry.namespace_id.desc": "名前空間ID",
  "domain.model.mo_namespace.namespaceentry.namespace_member_email.desc": "これがチームメンバーフォルダまたはアプリフォルダの場合、所有するチームメンバーのメールアドレス.",
  "domain.model.mo_namespace.namespaceentry.namespace_name.desc": "名前空間の名称",
  "domain.model.mo_namespace.namespaceentry.namespace_type.desc": "名前異空間のタイプ (app_folder, shared_folder, team_folder, または team_member_folder)",
  "domain.model.mo_namespace.namespaceentry.parent_shared_folder_id.desc": "設定されている場合、共有フォルダに内包されています.",
  "domain.model.mo_namespace.namespaceentry.path_display.desc": "パス (表示目的で大文字小文字を区別する).",
  "domain.model.mo_namespace.namespaceentry.revision.desc": "ファイルの現在バージョンの一意な識別子",
  "domain.model.mo_namespace.namespaceentry.server_modified.desc": "Dropbox上で最後に更新された日時",
  "domain.model.mo_namespace.namespaceentry.shared_folder_id.desc": "これが共有フォルダのマウントポイントである場合、ここにマウントされている共有フォルダのID。",
  "domain.model.mo_namespace.namespaceentry.size.desc": "ファイルサイズ(バイト単位)",
  "domain.model.mo_namespace.namespaceentry.tag.desc": "エントリーの種別`file`, `folder`, または `deleted`",
  "domain.model.mo_namespace.namespacemember.display_name.desc": "セッションのタイプ (web_session, desktop_client, または mobile_client)",
  "domain.model.mo_namespace.namespacemember.email.desc": "ユーザーのメールアドレス",
  "domain.model.mo_namespace.namespacemember.entry_access_type.desc": "ユーザーの共有ファイル・フォルダへのアクセスレベル (owner, editor, viewer, または viewer_no_comment)",
  "domain.model.mo_namespace.namespacemember.entry_is_inherited.desc": "メンバーのアクセス権限が上位フォルダから継承されている場合true",
  "domain.model.mo_namespace.namespacemember.group_name.desc": "グループ名称",
  "domain.model.mo_namespace.namespacemember.invitee_email.desc": "このフォルダに招待されたメールアドレス",
  "domain.model.mo_namespace.namespacemember.namespace_id.desc": "名前空間ID",
  "domain.model.mo_namespace.namespacemember.namespace_name.desc": "名前空間の名称",
  "domain.model.mo_namespace.namespacemember.namespace_type.desc": "名前異空間のタイプ (app_folder, shared_folder, team_folder, または team_member_folder)",
  "domain.model.mo_sharedfolder_member.sharedfoldermember.access_type.desc": "ユーザーの共有ファイル・フォルダへのアクセスレベル (owner, editor, viewer, または viewer_no_comment)",
  "domain.model.mo_sharedfolder_member.sharedfoldermember.account_id.desc": "ユーザーのアカウントID",
  "domain.model.mo_sharedfolder_member.sharedfoldermember.display_name.desc": "ユーザーのDropboxアカウントの表示名称",
  "domain.model.mo_sharedfolder_member.sharedfoldermember.email.desc": "ユーザーのメールアドレス",
  "domain.model.mo_sharedfolder_member.sharedfoldermember.is_inherited.desc": "メンバーのアクセス権限が上位フォルダから継承されている場合true",
  "domain.model.mo_sharedfolder_member.sharedfoldermember.group_id.desc": "グループID",
  "domain.model.mo_sharedfolder_member.sharedfoldermember.group_name.desc": "グループ名称",
  "domain.model.mo_sharedfolder_member.sharedfoldermember.invitee_email.desc": "このフォルダに招待されたメールアドレス",
  "domain.model.mo_sharedfolder_member.sharedfoldermember.is_inside_team_folder.desc": "フォルダがチームフォルダに内包されているかどうか",
  "domain.model.mo_sharedfolder_member.sharedfoldermember.is_team_folder.desc": "このフォルダがチームフォルダであるかどうか",
  "domain.model.mo_sharedfolder_member.sharedfoldermember.name.desc": "共有フォルダの名称",
  "domain.model.mo_sharedfolder_member.sharedfoldermember.parent_shared_folder_id.desc": "親共有フォルダのID. このフィールドはフォルダが他の共有フォルダに含まれる場合のみ設定されます.",
  "domain.model.mo_sharedfolder_member.sharedfoldermember.path_lower.desc": "共有フォルダのフルパス(小文字に変換済み).",
  "domain.model.mo_sharedfolder_member.sharedfoldermember.shared_folder_id.desc": "共有フォルダのID",
  "domain.model.mo_sharedfolder.sharedfolder.access_type.desc": "ユーザーの共有ファイル・フォルダへのアクセスレベル (owner, editor, viewer, または viewer_no_comment)",
  "domain.model.mo_sharedfolder.sharedfolder.is_inside_team_folder.desc": "フォルダがチームフォルダに内包されているかどうか",
  "domain.model.mo_sharedfolder.sharedfolder.is_team_folder.desc": "このフォルダがチームフォルダであるかどうか",
  "domain.model.mo_sharedfolder.sharedfolder.name.desc": "共有フォルダの名称",
  "domain.model.mo_sharedfolder.sharedfolder.parent_shared_folder_id.desc": "親共有フォルダのID. このフィールドはフォルダが他の共有フォルダに含まれる場合のみ設定されます.",
  "domain.model.mo_sharedfolder.sharedfolder.path_lower.desc": "共有フォルダのフルパス(小文字に変換済み).",
  "domain.model.mo_sharedfolder.sharedfolder.policy_member.desc": "だれがこの共有フォルダのメンバーに参加できるか (team, または anyone)",
  "domain.model.mo_sharedfolder.sharedfolder.shared_folder_id.desc": "共有フォルダのID",
  "domain.model.mo_sharedlink.metadata.expires.desc": "有効期限 (設定されている場合)",
  "domain.model.mo_sharedlink.metadata.id.desc": "ファイルまたはフォルダへのリンクのID",
  "domain.model.mo_sharedlink.metadata.name.desc": "リンク先ファイル名称",
  "domain.model.mo_sharedlink.metadata.path_lower.desc": "パス (すべて小文字に変換).",
  "domain.model.mo_sharedlink.metadata.tag.desc": "エントリーの種別 (file, または folder)",
  "domain.model.mo_sharedlink.metadata.url.desc": "共有リンクのURL.",
  "domain.model.mo_sharedlink.metadata.visibility.desc": "共有リンクの開示範囲",
  "domain.model.mo_sharedlink.sharedlinkmember.account_id.desc": "ユーザーのアカウントID",
  "domain.model.mo_sharedlink.sharedlinkmember.email.desc": "ユーザーのメールアドレス",
  "domain.model.mo_sharedlink.sharedlinkmember.expires.desc": "有効期限 (設定されている場合)",
  "domain.model.mo_sharedlink.sharedlinkmember.given_name.desc": "リンク所有者の名",
  "domain.model.mo_sharedlink.sharedlinkmember.name.desc": "リンク先ファイル名称",
  "domain.model.mo_sharedlink.sharedlinkmember.path_lower.desc": "パス (すべて小文字に変換).",
  "domain.model.mo_sharedlink.sharedlinkmember.shared_link_id.desc": "ファイルまたはフォルダへのリンクのID",
  "domain.model.mo_sharedlink.sharedlinkmember.status.desc": "チームにおけるメンバーのステータス(active\/invited\/suspended\/removed)",
  "domain.model.mo_sharedlink.sharedlinkmember.surname.desc": "リンク所有者の名字",
  "domain.model.mo_sharedlink.sharedlinkmember.tag.desc": "エントリーの種別 (file, または folder)",
  "domain.model.mo_sharedlink.sharedlinkmember.team_member_id.desc": "チームにおけるメンバーのID",
  "domain.model.mo_sharedlink.sharedlinkmember.url.desc": "共有リンクのURL.",
  "domain.model.mo_sharedlink.sharedlinkmember.visibility.desc": "共有リンクの開示範囲",
  "domain.model.mo_team.feature.has_team_file_events.desc": "このチームがファイルイベント機能を持っているかどうか",
  "domain.model.mo_team.feature.has_team_selective_sync.desc": "このチームがチーム選択型同期を有効化しているかどうか",
  "domain.model.mo_team.feature.has_team_shared_dropbox.desc": "このチームが共有されたチームルートを持っているかどうか",
  "domain.model.mo_team.feature.upload_api_rate_limit_count.desc": "この月に利用されたアップロードAPIコール回数",
  "domain.model.mo_team.feature.upload_api_rate_limit.desc": "毎月利用可能なアップロードAPIコール回数",
  "domain.model.mo_team.info.name.desc": "チームの名称",
  "domain.model.mo_team.info.num_licensed_users.desc": "このチームで利用可能なライセンス数",
  "domain.model.mo_team.info.num_provisioned_users.desc": "The number of accounts that have been invited or are already active members of the team.",
  "domain.model.mo_team.info.policy_emm_state.desc": "This describes the Enterprise Mobility Management (EMM) state for this team (disabled, optional, or required)",
  "domain.model.mo_team.info.policy_office_add_in.desc": "The admin policy around the Dropbox Office Add-In for this team (disabled, or enabled)",
  "domain.model.mo_team.info.policy_shared_folder_join.desc": "Who can join folders shared by team members (team, or anyone)",
  "domain.model.mo_team.info.policy_shared_folder_member.desc": "Which shared folders team members can join (from_team_only, or from_anyone)",
  "domain.model.mo_team.info.policy_shared_link_create.desc": "Who can view shared links owned by team members (default_public, default_team_only, or team_only)",
  "domain.model.mo_team.info.team_id.desc": "The ID of the team.",
  "domain.model.mo_teamfolder.teamfolder.is_team_shared_dropbox.desc": "",
  "domain.model.mo_teamfolder.teamfolder.name.desc": "The name of the team folder.",
  "domain.model.mo_teamfolder.teamfolder.status.desc": "The status of the team folder (active, archived, or archive_in_progress)",
  "domain.model.mo_teamfolder.teamfolder.sync_setting.desc": "The sync setting applied to this team folder (default, not_synced, or not_synced_inactive)",
  "domain.model.mo_teamfolder.teamfolder.team_folder_id.desc": "The ID of the team folder.",
  "domain.model.mo_usage.memberusage.allocated.desc": "The total space allocated to the user's account (bytes).",
  "domain.model.mo_usage.memberusage.allocation.desc": "The user's space allocation (individual, or team)",
  "domain.model.mo_usage.memberusage.email.desc": "Email address of the account",
  "domain.model.mo_usage.memberusage.used_bytes.desc": "The user's total space usage (bytes).",
  "domain.model.mo_usage.memberusage.used_gb.desc": "The user's total space usage (in GB, 1GB = 1024 MB).",
  "domain.usecase.uc_file_upload.uploadrow.file.desc": "ローカルファイルのパス",
  "domain.usecase.uc_file_upload.uploadrow.size.desc": "Local file size",
  "domain.usecase.uc_file_upload.uploadsummary.num_bytes.desc": "Total upload size (Bytes)",
  "domain.usecase.uc_file_upload.uploadsummary.num_files_error.desc": "The number of files failed or got an error.",
  "domain.usecase.uc_file_upload.uploadsummary.num_files_upload.desc": "The number of files uploaded or to upload.",
  "domain.usecase.uc_file_upload.uploadsummary.num_files_skip.desc": "The number of files skipped or to skip.",
  "domain.usecase.uc_file_upload.uploadsummary.num_api_call.desc": "The number of estimated upload API call for upload.",
  "infra.report.rp_model.transactionrow.reason": "Reason of failure or skipped operation",
  "infra.report.rp_model.transactionrow.status": "Status of the operation",
  "recipe.file.uploadrow.file.desc": "ローカルファイルのパス",
  "recipe.member.deleterow.email.desc": "Email address of the account",
  "recipe.member.detachrow.email.desc": "Email address of the account",
  "recipe.member.inviterow.email.desc": "Email address of the account",
  "recipe.member.inviterow.given_name.desc": "Given name of the account",
  "recipe.member.inviterow.surname.desc": "Surname of the account",
  "recipe.member.replicationrow.dst_email.desc": "Destination account's email address",
  "recipe.member.replicationrow.src_email.desc": "Source account's email address",
  "recipe.member.update.emailrow.from_email.desc": "Current Email address",
  "recipe.member.update.emailrow.to_email.desc": "New Email address",
  "recipe.member.update.profilerow.email.desc": "Email address of the account",
  "recipe.member.update.profilerow.given_name.desc": "Given name of the account",
  "recipe.member.update.profilerow.surname.desc": "Surname of the account",
  "dbx.err.general_error": "エラー: {{.Error}}",
  "dbx.err.access_denied": "この処理を行う権限がありません",
  "dbx.err.access_error/inside_osx_package": "Mac OS Xパッケージはこの方法で共有できません共有リンクを利用してください",
  "dbx.err.access_error/inside_public_folder": "Publicフォルダはこの方法で共有できません公開リンクを利用してください",
  "dbx.err.access_error/invalid_file": "指定されたファイルが見つかりません",
  "dbx.err.access_error/invalid_id": "指定された共有フォルダIDが有効ではありません",
  "dbx.err.access_error/invalid_team_folder_id": "指定されたチームフォルダIDは有効ではありません",
  "dbx.err.access_error/is_folder": "フォルダはこの方法で共有できませんフォルダ共有か共有リンクを利用してください",
  "dbx.err.access_error/no_access": "この認証されたアプリケーションにはチームフォルダの管理権限が与えられていません",
  "dbx.err.access_error/no_permission": "要求された処理を実行するために現在のユーザーでは権限が不足しています",
  "dbx.err.access_error/not_a_member": "ユーザーが共有フォルダのメンバーではないためアクセスすることができません",
  "dbx.err.access_error/unmounted": "この共有フォルダはまだ追加されていません(マウントされていません)",
  "dbx.err.account_id_not_found": "指定されたアカウントIDに一致するユーザーが見つかりません",
  "dbx.err.admin_not_active": "チーム管理者またはこのアプリケーションを認証したチーム管理者は、すでにチームのアクティブなメンバーではなくなっています",
  "dbx.err.already_mounted": "この共有フォルダはすでに追加されています(マウントされています)",
  "dbx.err.app_id_mismatch": "このアプリケーションで利用しているアクセストークンと認証されたアプリケーションが一致しません",
  "dbx.err.app_lacks_access": "ファイルリクエストはこのアプリケーションから利用できませんアプリフォルダ権限のみで利用できるアプリでは、アプリフォルダのみでファイルリクエストを利用できます",
  "dbx.err.app_not_found": "アプリケーションが見つかりません",
  "dbx.err.bad_cursor": "読み取りに失敗しました (カーソルが失効しています)",
  "dbx.err.bad_path/contains_app_folder": "アプリフォルダを含む共有フォルダはサポートされていません",
  "dbx.err.bad_path/contains_shared_folder": "共有フォルダを含む共有フォルダはサポートされていません",
  "dbx.err.bad_path/contains_team_folder": "チームフォルダを含む共有フォルダはサポートされていません",
  "dbx.err.bad_path/inside_app_folder": "アプリフォルダ内のフォルダを共有することはできません",
  "dbx.err.bad_path/inside_osx_package": "Mac OS Xパッケージ内のフォルダを共有することはできません",
  "dbx.err.bad_path/inside_public_folder": "Publicフォルダ内のフォルダはこの方法では共有できません公開リンクを利用してください",
  "dbx.err.bad_path/inside_shared_folder": "共有フォルダ以下のフォルダを共有することはできません",
  "dbx.err.bad_path/invalid_path": "指定されたパスは有効ではありません",
  "dbx.err.bad_path/is_app_folder": "アプリフォルダを共有することはできません",
  "dbx.err.bad_path/is_file": "指定されたパスはファイルです",
  "dbx.err.bad_path/is_osx_package": "Mac OS Xパッケージを共有することはできません",
  "dbx.err.bad_path/is_public_folder": "公開フォルダはこの方法では共有できません公開リンクを利用してください",
  "dbx.err.cannot_keep_account_and_delete_data": "Basicアカウントへの変換を行う際には遠隔削除を同時に行うことはできませんBasicアカウントへの変換を行う際には遠隔削除オプションを使用しないでください",
  "dbx.err.cannot_keep_account_and_transfer": "Basicアカウントへの変換を行う際には他のユーザーへデータを移行することはできません",
  "dbx.err.cannot_keep_invited_user_account": "招待済み状態のユーザーをBasicアカウントへ変換することはできません",
  "dbx.err.cannot_set_permissions": "権限を付与または削除することができませんでした",
  "dbx.err.cant_copy_shared_folder": "共有フォルダはコピーすることができません",
  "dbx.err.cant_move_folder_into_itself": "フォルダを同一パスに移動することはできません",
  "dbx.err.cant_move_shared_folder": "共有フォルダを指定された位置に移動することができません",
  "dbx.err.cant_nest_shared_folder": "この移動処理によって共有フォルダは入れ子になった共有フォルダになりますこの処理は許可されていません",
  "dbx.err.cant_transfer_ownership": "この移動処理は所有権の移転が発生します所有権移転を有効にするオプションを指定してこの処理をやり直すことができます",
  "dbx.err.conflicting_property_names": "プロパティのフィールドキーはすでにテンプレートに存在しています",
  "dbx.err.contacts_not_found": "このリストからコンタクトを削除することができませんでしたリストが手動で追加されたコンタクトだけであることを確認してください削除はキャンセルされました",
  "dbx.err.content_malformed": "指定されたコンテンツが不正であるためPaperへインポートすることができません",
  "dbx.err.conversion_error": "サムネイル変換処理に失敗しました",
  "dbx.err.cursor_error/expired_cursor": "読み取りに失敗しました (カーソルが失効しています)",
  "dbx.err.cursor_error/invalid_cursor": "読み取りに失敗しました (カーソルが無効です)",
  "dbx.err.cursor_error/reset": "読み取りに失敗しました (カーソルが無効です)読み取りに失敗しました (カーソルが無効です)",
  "dbx.err.cursor_error/wrong_user_in_cursor": "読み取りに失敗しました (カーソルに無効なユーザーが含まれます)",
  "dbx.err.device_session_not_found": "デバイスセッションが見つかりませんでした",
  "dbx.err.directory_restricted_off": "ディレクトリ制限オプションは利用できません",
  "dbx.err.disabled_for_team": "このDropbox Businessユーザーチームではファイルリクエストを利用できません",
  "dbx.err.disallowed_shared_link_policy": "このアカウントでは指定された共有リンクポリシーを選択することはできません",
  "dbx.err.doc_archived": "この操作はアーカイブされたPaperドキュメントには利用できません",
  "dbx.err.doc_deleted": "この操作は削除されたPaperドキュメントには利用できません",
  "dbx.err.doc_length_exceeded": "新規に作成されたPaperドキュメントが大きすぎますコンテンツを複数のドキュメントに分割してください",
  "dbx.err.doc_not_found": "要求されたドキュメントが見つかりません",
  "dbx.err.does_not_fit_template": "一つ以上のプロパティフィールドがテンプレートの仕様を満たしていません",
  "dbx.err.download_failed": "指定されたURLのダウンロードに失敗しましたURLがパスワードで保護されているか、指定されたパスワードが違います",
  "dbx.err.duplicate_user": "重複するユーザーを追加することはできませんグループに追加しようとしているメンバーのうち一人以上はすでにグループのメンバーです",
  "dbx.err.duplicated_or_nested_paths": "移動元と移動先のパスが重複しています",
  "dbx.err.email_address_too_long_to_be_disabled": "無効化するにはこのユーザのメールアドレスが長すぎます",
  "dbx.err.email_not_verified": "ユーザーのメールアドレスは確認済みである必要があります",
  "dbx.err.email_reserved_for_other_user": "このメールアドレスは他のユーザーがすでに利用しています",
  "dbx.err.email_unverified": "このユーザーのメールアドレスはまだ確認されていません",
  "dbx.err.empty_features_list": "機能リストを取得するにはすくなくとも一つ以上の機能を指定してください",
  "dbx.err.expired_access_token": "アクセストークンは失効しました",
  "dbx.err.external_id_already_in_use": "リクエストされた外部IDはすでに他のグループで利用されています",
  "dbx.err.external_id_and_new_external_id_unsafe": "外部IDと新しい外部IDの両方を使うのは安全ではありません",
  "dbx.err.external_id_used_by_other_user": "指定された外部IDはすでに他のチームメンバーが利用しています",
  "dbx.err.folder_name_already_used": "同じ名前のチームフォルダがすでに存在ます",
  "dbx.err.folder_name_reserved": "指定された名前は予約されており利用できません",
  "dbx.err.folder_not_found": "指定されたPaperフォルダが見つかりませんでした",
  "dbx.err.from_lookup/malformed_path": "指定されたパスはパス書式を満たしていません  ",
  "dbx.err.from_lookup/not_file": "操作はファイルを想定していますが、指定されたパスはファイルではありませんでした",
  "dbx.err.from_lookup/not_folder": "操作はフォルダを想定していますが、指定されたパスはフォルダはではありませんでした",
  "dbx.err.from_lookup/not_found": "指定されたパスには何もありませんでした",
  "dbx.err.from_lookup/restricted_content": "コンテンツは制限されているため転送することはできませんでしたたとえば、著作権侵害などの法的制限によります",
  "dbx.err.from_lookup/unsupported_content_type": "このコンテンツタイプへの操作はサポートされていません",
  "dbx.err.from_write/conflict/file": "競合するファイルがあります",
  "dbx.err.from_write/conflict/file_ancestor": "上位のパスにファイルがあるため、必要な親フォルダを作成することができませんでした",
  "dbx.err.from_write/conflict/folder": "競合するフォルダがあります",
  "dbx.err.from_write/disallowed_name": "名称に問題があるためファイルまたはフォルダを保存することができませんでした",
  "dbx.err.from_write/file": "競合するファイルがあります",
  "dbx.err.from_write/file_ancestor": "上位のパスにファイルがあるため、必要な親フォルダを作成することができませんでした",
  "dbx.err.from_write/folder": "競合するフォルダがあります",
  "dbx.err.from_write/insufficient_space": "データを書き込むために必要なDropboxの容量が不足しています",
  "dbx.err.from_write/malformed_path": "指定されたパスはパス書式を満たしていません  ",
  "dbx.err.from_write/no_write_permission": "このユーザーは指定された場所に書き込むための権限を持っていません",
  "dbx.err.from_write/team_folder": "このエンドポイントではチームフォルダを移動したり、削除することはできません",
  "dbx.err.from_write/too_many_write_operations": "ユーザーのDropboxに書き込み処理が集中しているため、一時的に新規の書き込み処理が中断されていますしばらくおいてから再実行してください",
  "dbx.err.group_access": "このユーザーは共有ファイルにグループ経由でアクセス権を持っていますグループ経由で共有されたファイルのメンバーシップを解除することはできません",
  "dbx.err.group_already_deleted": "このグループはすでに削除されています",
  "dbx.err.group_name_already_used": "指定されたグループ名はすでに他のグループに利用されています",
  "dbx.err.group_name_invalid": "グループ名が空白あるいは、利用できない文字が利用されています",
  "dbx.err.group_not_found": "一致するグループが見つかりませんでした指定されたグループIDに一致するグループが見つかりませんでした",
  "dbx.err.group_not_in_team": "指定されたグループはこのチームのものではありません外部のチームが管理するグループで共有されているため、メンバーを更新することはできません",
  "dbx.err.group_not_on_team": "このグループはこのチームのものではありません",
  "dbx.err.image_size_exceeded": "取り込まれたドキュメントに含まれる画像が大きすぎます. 現在の制限は1MBです. 注意: これはHTMLとデータURIで指定された場合に適用されます",
  "dbx.err.in_progress": "このプレビューはまだ生成中です",
  "dbx.err.inside_shared_folder": "共有フォルダの中に別の共有フォルダを追加することはできません",
  "dbx.err.insufficient_permissions": "このアカウントはこの操作を実行する権限がありません",
  "dbx.err.insufficient_plan": "現在のユーザーアカウントはこの操作を実行する権限がありませんたとえば、編集者から閲覧可能にダウングレードする場合です. このアクションはProまたはビジネスプランにアップグレードした場合に利用できます",
  "dbx.err.insufficient_quota": "現在のユーザーはファイルを移動またはコピーするために十分な空き容量を持っていません",
  "dbx.err.internal_error": "Dropbox側で処理の実行に失敗しました問題がないか処理結果を確認し、必要であれば再実行してくださいこれは滅多に発生することはありません",
  "dbx.err.invalid_access_token": "アクセストークンが無効です",
  "dbx.err.invalid_account_type/endpoint": "このアカウントタイプでは該当エンドポイントにアクセスする権限がありません",
  "dbx.err.invalid_account_type/feature": "このアカウントタイプではこの機能を利用する権限がありません",
  "dbx.err.invalid_arg": "与えられたデータが無効です",
  "dbx.err.invalid_async_job_id": "ジョブIDが無効です",
  "dbx.err.invalid_comment": "カスタムメッセージがコメント権限チェックを通過しませんでした",
  "dbx.err.invalid_copy_reference": "コピー参照が無効です",
  "dbx.err.invalid_cursor": "読み取りに失敗しました (カーソルが無効です)",
  "dbx.err.invalid_dropbox_id": "指定されたDropbox IDが無効です",
  "dbx.err.invalid_folder_name": "指定されたフォルダ名は利用できません",
  "dbx.err.invalid_location": "このフォルダではファイルリクエストは利用できません",
  "dbx.err.invalid_member": "指定されたメンバーが見つかりませんでした",
  "dbx.err.invalid_oauth1_token_info": "一部またはすべてのOAuth 1.0アクセストークンが無効です",
  "dbx.err.invalid_revision": "このリビジョンは無効ですおそらく存在しません.",
  "dbx.err.invalid_select_admin": "'Dropbox-API-Select-Admin'で指定されたユーザーはDropbox Businessのチーム管理者ではありません",
  "dbx.err.invalid_select_user": "'Dropbox-API-Select-User'で指定されたユーザーはチームメンバーではありません",
  "dbx.err.invalid_time_range": "無効な期間設定です",
  "dbx.err.invalid_url": "指定されたURLは無効です",
  "dbx.err.last_admin": "管理者は最低一人以上必要なため、管理権限を削除することができません",
  "dbx.err.list_error": "エラーが発生しました",
  "dbx.err.lookup_failed/closed": "アップロードセッションでデータを追加しようとしましたが、セッションはすでに閉じられています",
  "dbx.err.lookup_failed/correct_offset": "データが取得されたところまでのオフセットと一致しません",
  "dbx.err.lookup_failed/incorrect_offset/correct_offset": "データが取得されたところまでのオフセットと一致しません",
  "dbx.err.lookup_failed/not_closed": "セッションがupload_session\/finish_batchのまえに閉じる必要があります",
  "dbx.err.lookup_failed/not_found": "アップロードセッションIDが見つからないか失効していますアップロードセッションは48時間有効です",
  "dbx.err.lookup_failed/too_large": "最大ファイルサイズに達しているためアップロードセッションでデータを追加することができませんでした",
  "dbx.err.mapping_not_found": "トークン作成の対応づけが記録されていなかったため、このトークンは現在のチーム管理者に所属していません認証を実行した管理者を記録するために新しくアクセストークンを生成することを検討してください",
  "dbx.err.member_error/invalid_dropbox_id": "指定されたDropbox IDが無効です",
  "dbx.err.member_error/not_a_member": "指定されたDropbox IDは共有フォルダのメンバーではありません",
  "dbx.err.member_not_found": "メンバーが見つかりません",
  "dbx.err.member_not_in_group": "少なくとも一人以上のユーザーがグループのメンバーではありません",
  "dbx.err.members_not_in_team": "これらのメンバーはこのチームに所属していません",
  "dbx.err.new_owner_email_unverified": "指定された新しい所有者はまだメールアドレスの確認が取れていません",
  "dbx.err.new_owner_not_a_member": "指定された新しい所有者は共有フォルダのメンバーではありません",
  "dbx.err.new_owner_unmounted": "指定された新しい所有者はまだフォルダをDropboxに追加していません",
  "dbx.err.no_account": "指定されたアカウントIDは存在しませんでした",
  "dbx.err.no_explicit_access/access_error/invalid_id": "指定された共有フォルダIDが有効ではありません",
  "dbx.err.no_explicit_access/access_error/not_a_member": "ユーザーが共有フォルダのメンバーではないためアクセスすることができません",
  "dbx.err.no_explicit_access/access_error/unmounted": "この共有フォルダはまだ追加されていません(マウントされていません)",
  "dbx.err.no_explicit_access/automatic_group": "自動的に作成されたグループはチームフォルダにのみ追加することができます",
  "dbx.err.no_explicit_access/bad_member/automatic_group": "自動的に作成されたグループはチームフォルダにのみ追加することができます",
  "dbx.err.no_explicit_access/bad_member/group_deleted": "フォルダに追加しようとしたグループのうち一つ以上がすでに削除されています",
  "dbx.err.no_explicit_access/bad_member/group_not_on_team": "Sharing to a group that is not on the current user's team.",
  "dbx.err.no_explicit_access/bad_member/invalid_dropbox_id": "The value is the ID that could not be identified.",
  "dbx.err.no_explicit_access/bad_member/invalid_email": "The value is the e-email address that is malformed.",
  "dbx.err.no_explicit_access/bad_member/unverified_dropbox_id": "The value is the ID of the Dropbox user with an unverified e-mail address.  Invite unverified users by e-mail address instead of by their Dropbox ID.",
  "dbx.err.no_explicit_access/banned_member": "The current user has been banned.",
  "dbx.err.no_explicit_access/cant_share_outside_team": "Your team policy does not allow sharing outside of the team.",
  "dbx.err.no_explicit_access/email_unverified": "このユーザーのメールアドレスはまだ確認されていません",
  "dbx.err.no_explicit_access/group_deleted": "フォルダに追加しようとしたグループのうち一つ以上がすでに削除されています",
  "dbx.err.no_explicit_access/group_not_on_team": "Sharing to a group that is not on the current user's team.",
  "dbx.err.no_explicit_access/insufficient_plan": "現在のユーザーアカウントはこの操作を実行する権限がありませんAn example of this is when adding a read-only member. このアクションはProまたはビジネスプランにアップグレードした場合に利用できます",
  "dbx.err.no_explicit_access/invalid_dropbox_id": "The value is the ID that could not be identified.",
  "dbx.err.no_explicit_access/invalid_email": "The value is the e-email address that is malformed.",
  "dbx.err.no_explicit_access/invalid_id": "指定された共有フォルダIDが有効ではありません",
  "dbx.err.no_explicit_access/no_permission": "The current user does not have permission to perform this action.",
  "dbx.err.no_explicit_access/not_a_member": "ユーザーが共有フォルダのメンバーではないためアクセスすることができません",
  "dbx.err.no_explicit_access/rate_limit": "The current user has hit the limit of invites they can send per day. Try again in 24 hours.",
  "dbx.err.no_explicit_access/team_folder": "This action cannot be performed on a team shared folder.",
  "dbx.err.no_explicit_access/too_many_invitees": "The current user is trying to share with too many people at once.",
  "dbx.err.no_explicit_access/too_many_members": "The value is the member limit that was reached.",
  "dbx.err.no_explicit_access/too_many_pending_invites": "The value is the pending invite limit that was reached.",
  "dbx.err.no_explicit_access/unmounted": "この共有フォルダはまだ追加されていません(マウントされていません)",
  "dbx.err.no_explicit_access/unverified_dropbox_id": "The value is the ID of the Dropbox user with an unverified e-mail address.  Invite unverified users by e-mail address instead of by their Dropbox ID.",
  "dbx.err.no_new_data_specified": "None of new_email, new_given_name, new_surname, or new_external_id are specified.",
  "dbx.err.no_permission": "User does not have permission to perform this action on this member.",
  "dbx.err.not_a_folder": "The specified path is not a folder.",
  "dbx.err.not_found": "Not found.",
  "dbx.err.not_mountable": "The shared folder is not mountable. One example where this can occur is when the shared folder belongs within a team folder in the user's Dropbox.",
  "dbx.err.not_on_team": "UpdateFolderPolicyArg.member_policy was set even though user is not on a team.",
  "dbx.err.not_unmountable": "The shared folder can't be unmounted. One example where this can occur is when the shared folder's parent folder is also a shared folder that resides in the current user's Dropbox.",
  "dbx.err.paper_access_denied/not_paper_user": "The provided user has not used Paper yet.",
  "dbx.err.paper_access_denied/paper_disabled": "Paper is disabled.",
  "dbx.err.param_cannot_be_empty": "Parameter new_email cannot be empty.",
  "dbx.err.path": "",
  "dbx.err.path/conflict/file": "競合するファイルがあります",
  "dbx.err.path/conflict/file_ancestor": "上位のパスにファイルがあるため、必要な親フォルダを作成することができませんでした",
  "dbx.err.path/conflict/folder": "競合するフォルダがあります",
  "dbx.err.path/disallowed_name": "名称に問題があるためファイルまたはフォルダを保存することができませんでした",
  "dbx.err.path/file": "競合するファイルがあります",
  "dbx.err.path/file_ancestor": "上位のパスにファイルがあるため、必要な親フォルダを作成することができませんでした",
  "dbx.err.path/folder": "競合するフォルダがあります",
  "dbx.err.path/insufficient_space": "データを書き込むために必要なDropboxの容量が不足しています",
  "dbx.err.path/malformed_path": "指定されたパスはパス書式を満たしていません  ",
  "dbx.err.path/no_write_permission": "このユーザーは指定された場所に書き込むための権限を持っていません",
  "dbx.err.path/not_file": "操作はファイルを想定していますが、指定されたパスはファイルではありませんでした",
  "dbx.err.path/not_folder": "操作はフォルダを想定していますが、指定されたパスはフォルダはではありませんでした",
  "dbx.err.path/not_found": "指定されたパスには何もありませんでした",
  "dbx.err.path/restricted_content": "コンテンツは制限されているため転送することはできませんでしたたとえば、著作権侵害などの法的制限によります",
  "dbx.err.path/team_folder": "このエンドポイントではチームフォルダを移動したり、削除することはできません",
  "dbx.err.path/too_many_write_operations": "ユーザーのDropboxに書き込み処理が集中しているため、一時的に新規の書き込み処理が中断されていますしばらくおいてから再実行してください",
  "dbx.err.path/unsupported_content_type": "このコンテンツタイプへの操作はサポートされていません",
  "dbx.err.path_lookup/malformed_path": "指定されたパスはパス書式を満たしていません  ",
  "dbx.err.path_lookup/not_file": "操作はファイルを想定していますが、指定されたパスはファイルではありませんでした",
  "dbx.err.path_lookup/not_folder": "操作はフォルダを想定していますが、指定されたパスはフォルダはではありませんでした",
  "dbx.err.path_lookup/not_found": "指定されたパスには何もありませんでした",
  "dbx.err.path_lookup/restricted_content": "コンテンツは制限されているため転送することはできませんでしたたとえば、著作権侵害などの法的制限によります",
  "dbx.err.path_lookup/unsupported_content_type": "このコンテンツタイプへの操作はサポートされていません",
  "dbx.err.path_write/conflict/file": "競合するファイルがあります",
  "dbx.err.path_write/conflict/file_ancestor": "上位のパスにファイルがあるため、必要な親フォルダを作成することができませんでした",
  "dbx.err.path_write/conflict/folder": "競合するフォルダがあります",
  "dbx.err.path_write/disallowed_name": "名称に問題があるためファイルまたはフォルダを保存することができませんでした",
  "dbx.err.path_write/file": "競合するファイルがあります",
  "dbx.err.path_write/file_ancestor": "上位のパスにファイルがあるため、必要な親フォルダを作成することができませんでした",
  "dbx.err.path_write/folder": "競合するフォルダがあります",
  "dbx.err.path_write/insufficient_space": "データを書き込むために必要なDropboxの容量が不足しています",
  "dbx.err.path_write/malformed_path": "指定されたパスはパス書式を満たしていません  ",
  "dbx.err.path_write/no_write_permission": "このユーザーは指定された場所に書き込むための権限を持っていません",
  "dbx.err.path_write/team_folder": "このエンドポイントではチームフォルダを移動したり、削除することはできません",
  "dbx.err.path_write/too_many_write_operations": "ユーザーのDropboxに書き込み処理が集中しているため、一時的に新規の書き込み処理が中断されていますしばらくおいてから再実行してください",
  "dbx.err.persistent_id_disabled": "パーシステントIDはパーシステントIDを利用するSAML設定を利用するチームのみで利用可能です",
  "dbx.err.persistent_id_used_by_other_user": "パーシステントIDはすでに他のチームメンバーに利用されています",
  "dbx.err.properties_error/does_not_fit_template": "一つ以上のプロパティフィールドがテンプレートの仕様を満たしていません",
  "dbx.err.properties_error/malformed_path": "",
  "dbx.err.properties_error/not_file": "操作はファイルを想定していますが、指定されたパスはファイルではありませんでした",
  "dbx.err.properties_error/not_folder": "操作はフォルダを想定していますが、指定されたパスはフォルダはではありませんでした",
  "dbx.err.properties_error/not_found": "指定されたパスには何もありませんでした",
  "dbx.err.properties_error/path/malformed_path": "",
  "dbx.err.properties_error/path/not_file": "操作はファイルを想定していますが、指定されたパスはファイルではありませんでした",
  "dbx.err.properties_error/path/not_folder": "操作はフォルダを想定していますが、指定されたパスはフォルダはではありませんでした",
  "dbx.err.properties_error/path/not_found": "指定されたパスには何もありませんでした",
  "dbx.err.properties_error/path/restricted_content": "コンテンツは制限されているため転送することはできませんでしたたとえば、著作権侵害などの法的制限によります",
  "dbx.err.properties_error/property_field_too_large": "One or more of the supplied property field values is too large.",
  "dbx.err.properties_error/property_group_not_found": "No property group was found.",
  "dbx.err.properties_error/restricted_content": "You do not have permission to modify this template.",
  "dbx.err.properties_error/template_not_found": "Template does not exist for the given identifier.",
  "dbx.err.properties_error/unsupported_folder": "This folder cannot be tagged. Tagging folders is not supported for team-owned templates.",
  "dbx.err.property_field_too_large": "One or more of the supplied property field values is too large.",
  "dbx.err.property_group_already_exists": "A property group associated with this template and file already exists.",
  "dbx.err.property_group_lookup/property_group_not_found": "No property group was found.",
  "dbx.err.rate_limit": "The user has reached the rate limit for invitations.",
  "dbx.err.recipient_not_verified": "The recipient user's email is not verified.",
  "dbx.err.relinquish_folder_membership_error/access_error/invalid_id": "指定された共有フォルダIDが有効ではありません",
  "dbx.err.relinquish_folder_membership_error/access_error/not_a_member": "ユーザーが共有フォルダのメンバーではないためアクセスすることができません",
  "dbx.err.relinquish_folder_membership_error/access_error/unmounted": "この共有フォルダはまだ追加されていません(マウントされていません)",
  "dbx.err.relinquish_folder_membership_error/folder_owner": "The current user is the owner of the shared folder. Owners cannot relinquish membership to their own folders. Try unsharing or transferring ownership first.",
  "dbx.err.relinquish_folder_membership_error/group_access": "The current user has access to the shared folder via a group.  You can't relinquish membership to folders shared via groups.",
  "dbx.err.relinquish_folder_membership_error/invalid_id": "指定された共有フォルダIDが有効ではありません",
  "dbx.err.relinquish_folder_membership_error/mounted": "The shared folder is currently mounted.  Unmount the shared folder before relinquishing membership.",
  "dbx.err.relinquish_folder_membership_error/no_explicit_access": "The current user only has inherited access to the shared folder.  You can't relinquish inherited membership to folders.",
  "dbx.err.relinquish_folder_membership_error/no_permission": "The current user does not have permission to perform this action.",
  "dbx.err.relinquish_folder_membership_error/not_a_member": "ユーザーが共有フォルダのメンバーではないためアクセスすることができません",
  "dbx.err.relinquish_folder_membership_error/team_folder": "This action cannot be performed on a team shared folder.",
  "dbx.err.relinquish_folder_membership_error/unmounted": "この共有フォルダはまだ追加されていません(マウントされていません)",
  "dbx.err.remove_folder_member_error/access_error/invalid_id": "指定された共有フォルダIDが有効ではありません",
  "dbx.err.remove_folder_member_error/access_error/not_a_member": "ユーザーが共有フォルダのメンバーではないためアクセスすることができません",
  "dbx.err.remove_folder_member_error/access_error/unmounted": "この共有フォルダはまだ追加されていません(マウントされていません)",
  "dbx.err.remove_folder_member_error/folder_owner": "The target user is the owner of the shared folder. You can't remove this user until ownership has been transferred to another member.",
  "dbx.err.remove_folder_member_error/group_access": "The target user has access to the shared folder via a group.",
  "dbx.err.remove_folder_member_error/invalid_dropbox_id": "指定されたDropbox IDが無効です",
  "dbx.err.remove_folder_member_error/invalid_id": "指定された共有フォルダIDが有効ではありません",
  "dbx.err.remove_folder_member_error/member_error/invalid_dropbox_id": "指定されたDropbox IDが無効です",
  "dbx.err.remove_folder_member_error/member_error/not_a_member": "指定されたDropbox IDは共有フォルダのメンバーではありません",
  "dbx.err.remove_folder_member_error/no_permission": "The current user does not have permission to perform this action.",
  "dbx.err.remove_folder_member_error/not_a_member": "指定されたDropbox IDは共有フォルダのメンバーではありません",
  "dbx.err.remove_folder_member_error/team_folder": "This action cannot be performed on a team shared folder.",
  "dbx.err.remove_folder_member_error/too_many_files": "This shared folder has too many files for leaving a copy. You can still remove this user without leaving a copy.",
  "dbx.err.remove_folder_member_error/unmounted": "この共有フォルダはまだ追加されていません(マウントされていません)",
  "dbx.err.remove_last_admin": "The user is the last admin of the team, so it cannot be removed from it.",
  "dbx.err.removed_and_transfer_admin_should_differ": "Expected removed user and transfer_admin user to be different.",
  "dbx.err.removed_and_transfer_dest_should_differ": "Expected removed user and transfer_dest user to be different.",
  "dbx.err.reset": "読み取りに失敗しました (カーソルが無効です)",
  "dbx.err.restricted_content": "You do not have permission to modify this template.",
  "dbx.err.retry_after": "The number of seconds that the app should wait before making another request. The default for this field is 1.",
  "dbx.err.revision_mismatch": "The provided revision does not match the document head.",
  "dbx.err.set_profile_disallowed": "Modifying deleted users is not allowed.",
  "dbx.err.settings_error/invalid_settings": "The given settings are invalid (for example, all attributes of the SharedLinkSettings are empty, the requested visibility is RequestedVisibility.password but the SharedLinkSettings.link_password is missing, SharedLinkSettings.expires is set to the past, etc.).",
  "dbx.err.settings_error/not_authorized": "User is not allowed to modify the settings of this link. Note that basic users can only set RequestedVisibility.public as the SharedLinkSettings.requested_visibility and cannot set SharedLinkSettings.expires.",
  "dbx.err.shared_link_access_denied": "The caller is not allowed to access this shared link.",
  "dbx.err.shared_link_already_exists": "The shared link already exists.",
  "dbx.err.shared_link_is_directory": "Directories cannot be retrieved by this endpoint.",
  "dbx.err.shared_link_malformed": "Shared link is malformed.",
  "dbx.err.shared_link_not_found": "The shared link wasn't found.",
  "dbx.err.some_users_are_excluded": "Some of the users are on the excluded users list and can't have custom quota set.",
  "dbx.err.status_error/active": "The folder is active and the operation did not succeed.",
  "dbx.err.status_error/archive_in_progress": "The folder is being archived and the operation did not succeed.",
  "dbx.err.status_error/archived": "The folder is archived and the operation did not succeed.",
  "dbx.err.suspend_inactive_user": "The user is not active, so it cannot be suspended.",
  "dbx.err.suspend_last_admin": "The user is the last admin of the team, so it cannot be suspended.",
  "dbx.err.sync_settings_error/malformed_path": "指定されたパスはパス書式を満たしていません  ",
  "dbx.err.sync_settings_error/not_file": "操作はファイルを想定していますが、指定されたパスはファイルではありませんでした",
  "dbx.err.sync_settings_error/not_folder": "操作はフォルダを想定していますが、指定されたパスはフォルダはではありませんでした",
  "dbx.err.sync_settings_error/not_found": "指定されたパスには何もありませんでした",
  "dbx.err.sync_settings_error/path/malformed_path": "指定されたパスはパス書式を満たしていません  ",
  "dbx.err.sync_settings_error/path/not_file": "操作はファイルを想定していますが、指定されたパスはファイルではありませんでした",
  "dbx.err.sync_settings_error/path/not_folder": "操作はフォルダを想定していますが、指定されたパスはフォルダはではありませんでした",
  "dbx.err.sync_settings_error/path/not_found": "指定されたパスには何もありませんでした",
  "dbx.err.sync_settings_error/path/restricted_content": "コンテンツは制限されているため転送することはできませんでしたたとえば、著作権侵害などの法的制限によります",
  "dbx.err.sync_settings_error/path/unsupported_content_type": "このコンテンツタイプへの操作はサポートされていません",
  "dbx.err.sync_settings_error/restricted_content": "コンテンツは制限されているため転送することはできませんでしたたとえば、著作権侵害などの法的制限によります",
  "dbx.err.sync_settings_error/unsupported_combination": "Setting this combination of sync settings simultaneously is not supported.",
  "dbx.err.sync_settings_error/unsupported_configuration": "The specified configuration is not supported.",
  "dbx.err.sync_settings_error/unsupported_content_type": "このコンテンツタイプへの操作はサポートされていません",
  "dbx.err.system_managed_group_disallowed": "System-managed group cannot be manually created.",
  "dbx.err.team_folder": "This action cannot be performed on a team shared folder.",
  "dbx.err.team_license_limit": "Team is full. The organization has no available licenses.",
  "dbx.err.team_policy_disallows_member_policy": "Team policy is more restrictive than ShareFolderArg.member_policy.",
  "dbx.err.team_shared_dropbox_error/disallowed": "This action is not allowed for a shared team root.",
  "dbx.err.template_attribute_too_large": "The template name, description or one or more of the property field keys is too large.",
  "dbx.err.template_not_found": "Template does not exist for the given identifier.",
  "dbx.err.to/conflict/file": "競合するファイルがあります",
  "dbx.err.to/conflict/file_ancestor": "上位のパスにファイルがあるため、必要な親フォルダを作成することができませんでした",
  "dbx.err.to/conflict/folder": "競合するフォルダがあります",
  "dbx.err.to/disallowed_name": "名称に問題があるためファイルまたはフォルダを保存することができませんでした",
  "dbx.err.to/file": "競合するファイルがあります",
  "dbx.err.to/file_ancestor": "上位のパスにファイルがあるため、必要な親フォルダを作成することができませんでした",
  "dbx.err.to/folder": "競合するフォルダがあります",
  "dbx.err.to/insufficient_space": "データを書き込むために必要なDropboxの容量が不足しています",
  "dbx.err.to/malformed_path": "指定されたパスはパス書式を満たしていません  ",
  "dbx.err.to/no_write_permission": "このユーザーは指定された場所に書き込むための権限を持っていません",
  "dbx.err.to/team_folder": "このエンドポイントではチームフォルダを移動したり、削除することはできません",
  "dbx.err.to/too_many_write_operations": "ユーザーのDropboxに書き込み処理が集中しているため、一時的に新規の書き込み処理が中断されていますしばらくおいてから再実行してください",
  "dbx.err.too_large": "The folder or a file is too large to download.",
  "dbx.err.too_many_files": "There are too many files in one request. Please retry with fewer files.",
  "dbx.err.too_many_properties": "There are too many properties in the changed template. The maximum number of properties per template is 32.",
  "dbx.err.too_many_templates": "There are too many templates for the team.",
  "dbx.err.too_many_users": "A maximum of 1000 users can be set for a single call.",
  "dbx.err.too_many_write_operations": "ユーザーのDropboxに書き込み処理が集中しているため、一時的に新規の書き込み処理が中断されていますしばらくおいてから再実行してください",
  "dbx.err.transfer_admin_is_not_admin": "Specified transfer_admin user is not a team admin.",
  "dbx.err.transfer_admin_user_not_found": "No matching user found for the argument transfer_admin_id.",
  "dbx.err.transfer_admin_user_not_in_team": "The provided transfer_admin_id does not exist on this team.",
  "dbx.err.transfer_dest_user_not_found": "No matching user found for the argument transfer_dest_id.",
  "dbx.err.transfer_dest_user_not_in_team": "The provided transfer_dest_id does not exist on this team.",
  "dbx.err.unshare_folder_error/access_error/invalid_id": "指定された共有フォルダIDが有効ではありません",
  "dbx.err.unshare_folder_error/access_error/not_a_member": "ユーザーが共有フォルダのメンバーではないためアクセスすることができません",
  "dbx.err.unshare_folder_error/access_error/unmounted": "この共有フォルダはまだ追加されていません(マウントされていません)",
  "dbx.err.unshare_folder_error/invalid_id": "指定された共有フォルダIDが有効ではありません",
  "dbx.err.unshare_folder_error/no_permission": "The current user does not have permission to perform this action.",
  "dbx.err.unshare_folder_error/not_a_member": "ユーザーが共有フォルダのメンバーではないためアクセスすることができません",
  "dbx.err.unshare_folder_error/team_folder": "This action cannot be performed on a team shared folder.",
  "dbx.err.unshare_folder_error/too_many_files": "This shared folder has too many files to be unshared.",
  "dbx.err.unshare_folder_error/unmounted": "この共有フォルダはまだ追加されていません(マウントされていません)",
  "dbx.err.unspecified_transfer_admin_id": "The transfer_admin_id argument must be provided when file transfer is requested.",
  "dbx.err.unsupported_content": "The file content is not supported for preview generation.",
  "dbx.err.unsupported_extension": "The file extension is not supported preview generation.",
  "dbx.err.unsupported_file": "This file type cannot be downloaded directly.",
  "dbx.err.unsupported_folder": "This folder cannot be tagged. Tagging folders is not supported for team-owned templates.",
  "dbx.err.unsupported_image": "The image cannot be converted to a thumbnail.",
  "dbx.err.unsupported_link_type": "This type of link is not supported.",
  "dbx.err.unsuspend_non_suspended_member": "The user is unsuspended, so it cannot be unsuspended again.",
  "dbx.err.user_cannot_be_manager_of_company_managed_group": "A company-managed group cannot be managed by a user.",
  "dbx.err.user_data_already_transferred": "User's data has already been transferred to another user.",
  "dbx.err.user_data_cannot_be_transferred": "User files aren't transferable anymore.",
  "dbx.err.user_data_is_being_transferred": "The user's data is being transferred. Please wait some time before retrying.",
  "dbx.err.user_error/email_unverified": "The current user must verify the account e-mail address before performing this action.",
  "dbx.err.user_must_be_active_to_be_owner": "A suspended user cannot be added to a group as GroupAccessType.owner.",
  "dbx.err.user_not_found": "No matching user found. The provided team_member_id, email, or external_id does not exist on this team.",
  "dbx.err.user_not_in_team": "The user is not a member of the team.",
  "dbx.err.user_not_removed": "No matching removed user found for the argument user.",
  "dbx.err.user_suspended": "The user has been suspended.",
  "dbx.err.user_unrecoverable": "The user is not recoverable.",
  "dbx.err.users_not_found": "These users were not found in Dropbox.",
  "dbx.err.users_not_in_team": "At least one of the users is not part of your team.",
  "dbx.err.id_not_found": "ID not found",
  "dbx.err.validation_error": "There was an error validating the request. For example, the title was invalid, or there were disallowed characters in the destination path."
}
